Workbook

Sheet Cover
B2: Delivery Hero SE
B3: Income Statement Model & Growth Analysis
B4: FY2021A - FY2025A Actuals | FY2026E - FY2028E Forecast | EUR million unless noted
B6: Contents
B7: 1. Assumptions & Forecast Drivers
B8: 2. Consolidated Income Statement (FY21A-FY28E)
B9: 3. Segment Revenue & GMV Detail (growth by region)
B10: 4. Growth Analysis Dashboard (KPIs & charts)
B12: Company snapshot
B13: Ticker / Exchange | C13: DHER - Frankfurt / XETRA (Deutsche Börse)
B14: Sector | C14: Online food delivery & quick commerce ("Everyday App")
B15: Segments | C15: Asia, MENA, Europe, Americas, Integrated Verticals
B16: Fiscal year end | C16: 31 December
B17: Reporting currency | C17: EUR
B19: Notes & sourcing
B20: Sources: Delivery Hero SE press releases & trading updates (Q4/FY2021-FY2025), FY2024 Annual Report, stockanalysis.com aggregated financials. FY2026-2028 = model forecast built on company FY2026 guidance (issued w/ Q4 2025 results, Feb-2026) and illustrative assumptions thereafter. All figures EUR million unless noted. Historical consolidated P&L figures are as-reported IFRS group results; "Total Segment Revenue" and GMV are Delivery Hero's non-IFRS operating metrics reported alongside the IFRS statements and reconciled via an eliminations/other line. Blue text = hardcoded input/actual; black text = formula.
B28: Legend
B29: Historical actual (hardcoded)
B30: Forecast assumption (input)
B31: Calculated (formula)

Sheet Assumptions
B2: Forecast Assumptions & Drivers
B3: FY2026E guided by company outlook (Feb-2026 FY2025 results); FY2027E-FY2028E are illustrative model assumptions
B5: Group-level operating assumptions
C6: FY2026E | D6: FY2027E | E6: FY2028E | F6: Note
B7: GMV growth, LFL (%) | C7: 0.09 | D7: 0.085 | E7: 0.08 | F7: FY26: co. guidance 8-10% LFL (mid); FY27-28: illustrative deceleration
B8: Segment revenue -> IFRS revenue conversion (%) | C8: 0.955 | D8: 0.955 | E8: 0.955 | F8: Historical avg. IFRS revenue / Total Segment Revenue ~89.6-96.1%; recent-yr avg held flat
B9: Gross margin (%) | C9: 0.255 | D9: 0.263 | E9: 0.27 | F9: Gradual mix-driven gross margin recovery toward FY23 levels (~29.9%)
B10: Adjusted EBITDA margin, % of Total Segment Revenue | C10: 0.0545 | D10: 0.062 | E10: 0.07 | F10: FY26E co. guided EUR 910-960m (up-to-mid-single-digit % growth) implies temporary margin dip before re-expansion toward the 5-8%-of-GMV 2030 target
B11: D&A, % of revenue | C11: 0.021 | D11: 0.02 | E11: 0.019 | F11: Recent run-rate D&A/revenue, gradually declining with operating leverage
B12: Net financial result, EUR m (expense) | C12: -230 | D12: -180 | E12: -140 | F12: Declining net interest expense as leverage falls & FCF turns durably positive
B13: Effective cash tax expense, EUR m | C13: -95 | D13: -110 | E13: -125 | F13: Cash tax roughly flat-to-up with profitable-country mix; DTA effects excluded
B14: Diluted shares outstanding, million | C14: 300 | D14: 301 | E14: 302 | F14: ~flat; modest dilution from employee share plans, no major buyback assumed
B16: Segment mix — Total Segment Revenue growth by region, as-reported YoY (%)
C17: FY2026E | D17: FY2027E | E17: FY2028E | F17: Note
B18: Asia | C18: 0.09 | D18: 0.08 | E18: 0.075 | F18: FY25A +8.5%; Q4-25 returned to GMV growth (S. Korea)
B19: MENA | C19: 0.16 | D19: 0.145 | E19: 0.13 | F19: FY25A +14.4%; continued robust GMV (talabat)
B20: Europe | C20: 0.24 | D20: 0.19 | E20: 0.16 | F20: FY25A +31.4%; Foodpanda/Glovo momentum, deceleration assumed
B21: Americas | C21: 0.14 | D21: 0.12 | E21: 0.11 | F21: FY25A +12.6%; steady order growth
B22: Integrated Verticals (Quick Commerce) | C22: 0.2 | D22: 0.17 | E22: 0.15 | F22: FY25A +17.7%; QC GMV approaching EUR 10bn in FY26E
B24: All cells shaded gold are hard-coded model inputs — change them to flex the FY2026E-FY2028E forecast; every other cell in the Income Statement and Segment Detail sheets recalculates automatically. FY2026E group guidance (Total Segment Revenue LFL growth, GMV LFL growth, Adjusted EBITDA of EUR 910-960m) is sourced from Delivery Hero's FY2025 results / FY2026 outlook (Feb-2026); FY2027E-FY2028E and all segment-level splits are illustrative modeling assumptions, not company guidance.
B29: Historical actuals reference (for context — not inputs)
B30: FY2025A Adjusted EBITDA: >EUR 900m (final audited figure TBD at time of modeling, co. reported "above EUR 900.0m", +30% YoY). FY2024A Adjusted EBITDA: EUR 692.5m (revised down from EUR 750m preliminary due to Italy rider legal provisions). FY2023A Adjusted EBITDA: EUR 253.3m.

Sheet Segment Detail
B2: Segment Revenue & GMV Detail — Growth by Region
B3: EUR million unless noted. Segments: Asia, MENA, Europe, Americas, Integrated Verticals (Quick Commerce)
B5: Total Segment Revenue by region (non-IFRS operating metric, as reported)
C6: FY2023A | D6: FY2024A | E6: FY2025A | F6: FY2026E | G6: FY2027E | H6: FY2028E | I6: '23-'25 CAGR | J6: '25-'28E CAGR
B7: Asia | C7: 3729.3 | D7: 4071.9 | E7: 4417.7 | F7: =E7*(1+Assumptions!C18) -> 4815.293 | G7: =F7*(1+Assumptions!D18) -> 5200.5164 | H7: =G7*(1+Assumptions!E18) -> 5590.5552 | I7: =(E7/C7)^(1/2)-1 -> 0.088389766 | J7: =(H7/E7)^(1/3)-1 -> 0.081648716
B8: MENA | C8: 2700.8 | D8: 3527.8 | E8: 4033.7 | F8: =E8*(1+Assumptions!C19) -> 4679.092 | G8: =F8*(1+Assumptions!D19) -> 5357.5603 | H8: =G8*(1+Assumptions!E19) -> 6054.0432 | I8: =(E8/C8)^(1/2)-1 -> 0.22209674 | J8: =(H8/E8)^(1/3)-1 -> 0.14493449
B9: Europe | C9: 1522.4 | D9: 1891.9 | E9: 2486.3 | F9: =E9*(1+Assumptions!C20) -> 3083.012 | G9: =F9*(1+Assumptions!D20) -> 3668.7843 | H9: =G9*(1+Assumptions!E20) -> 4255.7898 | I9: =(E9/C9)^(1/2)-1 -> 0.27794563 | J9: =(H9/E9)^(1/3)-1 -> 0.19621399
B10: Americas | C10: 651 | D10: 939.6 | E10: 1057.6 | F10: =E10*(1+Assumptions!C21) -> 1205.664 | G10: =F10*(1+Assumptions!D21) -> 1350.3437 | H10: =G10*(1+Assumptions!E21) -> 1498.8815 | I10: =(E10/C10)^(1/2)-1 -> 0.27458918 | J10: =(H10/E10)^(1/3)-1 -> 0.12326429
B11: Integrated Verticals (Quick Commerce) | C11: 2162.1 | D11: 2709.8 | E11: 3189 | F11: =E11*(1+Assumptions!C22) -> 3826.8 | G11: =F11*(1+Assumptions!D22) -> 4477.356 | H11: =G11*(1+Assumptions!E22) -> 5148.9594 | I11: =(E11/C11)^(1/2)-1 -> 0.21447721 | J11: =(H11/E11)^(1/3)-1 -> 0.17315388
B12: Sum of segments | C12: =SUM(C7:C11) -> 10765.6 | D12: =SUM(D7:D11) -> 13141 | E12: =SUM(E7:E11) -> 15184.3 | F12: =SUM(F7:F11) -> 17609.861 | G12: =SUM(G7:G11) -> 20054.561 | H12: =SUM(H7:H11) -> 22548.229
B13: Eliminations & other (reconciling item) | C13: =C14-C12 -> 334.4 | D13: =D14-D12 -> -344.6 | E13: =E14-E12 -> -380.9 | F13: =F12*($E13/$E12) -> -441.74549 | G13: =G12*($E13/$E12) -> -503.07108 | H13: =H12*($E13/$E12) -> -565.62505
B14: Total Segment Revenue | C14: 11100 | D14: 12796.4 | E14: 14803.4 | F14: =F12+F13 -> 17168.116 | G14: =G12+G13 -> 19551.49 | H14: =H12+H13 -> 21982.604 | I14: =(E14/C14)^(1/2)-1 -> 0.15483317 | J14: =(H14/E14)^(1/3)-1 -> 0.14087804
B16: FY2023A-FY2025A: company-reported actuals. FY2026E-FY2028E: segment revenue grown at the assumed as-reported YoY rate per region (Assumptions sheet); eliminations held at the FY2025A ratio to segment sum.
B18: Segment revenue growth, YoY (%)
C19: FY2023A | D19: FY2024A | E19: FY2025A | F19: FY2026E | G19: FY2027E | H19: FY2028E
B20: Asia | C20: n/a | D20: =D7/C7-1 -> 0.091867106 | E20: =E7/D7-1 -> 0.0849235 | F20: =F7/E7-1 -> 0.09 | G20: =G7/F7-1 -> 0.08 | H20: =H7/G7-1 -> 0.075
B21: MENA | C21: n/a | D21: =D8/C8-1 -> 0.30620557 | E21: =E8/D8-1 -> 0.14340382 | F21: =F8/E8-1 -> 0.16 | G21: =G8/F8-1 -> 0.145 | H21: =H8/G8-1 -> 0.13
B22: Europe | C22: n/a | D22: =D9/C9-1 -> 0.24270888 | E22: =E9/D9-1 -> 0.31418151 | F22: =F9/E9-1 -> 0.24 | G22: =G9/F9-1 -> 0.19 | H22: =H9/G9-1 -> 0.16
B23: Americas | C23: n/a | D23: =D10/C10-1 -> 0.44331797 | E23: =E10/D10-1 -> 0.12558536 | F23: =F10/E10-1 -> 0.14 | G23: =G10/F10-1 -> 0.12 | H23: =H10/G10-1 -> 0.11
B24: Integrated Verticals | C24: n/a | D24: =D11/C11-1 -> 0.25331853 | E24: =E11/D11-1 -> 0.17683962 | F24: =F11/E11-1 -> 0.2 | G24: =G11/F11-1 -> 0.17 | H24: =H11/G11-1 -> 0.15
B25: Total Segment Revenue | C25: n/a | D25: =D14/C14-1 -> 0.15282883 | E25: =E14/D14-1 -> 0.15684099 | F25: =F14/E14-1 -> 0.15974138 | G25: =G14/F14-1 -> 0.13882561 | H25: =H14/G14-1 -> 0.1243442
B27: Revenue mix, % of Total Segment Revenue
C28: FY2023A | D28: FY2024A | E28: FY2025A | F28: FY2026E | G28: FY2027E | H28: FY2028E
B29: Asia | C29: =C7/C14 -> 0.33597297 | D29: =D7/D14 -> 0.31820668 | E29: =E7/E14 -> 0.29842469 | F29: =F7/F14 -> 0.28047883 | G29: =G7/G14 -> 0.2659908 | H29: =H7/H14 -> 0.25431724
B30: MENA | C30: =C8/C14 -> 0.24331532 | D30: =D8/D14 -> 0.27568691 | E30: =E8/E14 -> 0.2724847 | F30: =F8/F14 -> 0.27254546 | G30: =G8/G14 -> 0.27402313 | H30: =H8/H14 -> 0.27540155
B31: Europe | C31: =C9/C14 -> 0.13715315 | D31: =D9/D14 -> 0.14784627 | E31: =E9/E14 -> 0.16795466 | F31: =F9/F14 -> 0.17957778 | G31: =G9/G14 -> 0.1876473 | H31: =H9/H14 -> 0.19359807
B32: Americas | C32: =C10/C14 -> 0.058648649 | D32: =D10/D14 -> 0.073426901 | E32: =E10/E14 -> 0.071443047 | F32: =F10/F14 -> 0.070226927 | G32: =G10/G14 -> 0.069066025 | H32: =H10/H14 -> 0.068184892
B33: Integrated Verticals | C33: =C11/C14 -> 0.19478378 | D33: =D11/D14 -> 0.21176268 | E33: =E11/E14 -> 0.21542348 | F33: =F11/F14 -> 0.22290158 | G33: =G11/G14 -> 0.22900332 | H33: =H11/H14 -> 0.23422882
B35: Gross Merchandise Value (GMV) by region
C36: FY2023A | D36: FY2024A | E36: FY2025A | F36: FY2026E | G36: FY2027E | H36: FY2028E
B37: Asia | C37: n/a | D37: 23407.4 | E37: 20779.7 | F37: =$E37/$E$41*F41 -> 22649.873 | G37: =$E37/$E$41*G41 -> 24575.112 | H37: =$E37/$E$41*H41 -> 26541.121
B38: MENA | C38: n/a | D38: 12825.9 | E38: 14644.3 | F38: =$E38/$E$41*F41 -> 15962.287 | G38: =$E38/$E$41*G41 -> 17319.081 | H38: =$E38/$E$41*H41 -> 18704.608
B39: Europe | C39: n/a | D39: 8878.7 | E39: 9693.2 | F39: =$E39/$E$41*F41 -> 10565.588 | G39: =$E39/$E$41*G41 -> 11463.663 | H39: =$E39/$E$41*H41 -> 12380.756
B40: Americas | C40: n/a | D40: 3642 | E40: 4079.6 | F40: =$E40/$E$41*F41 -> 4446.764 | G40: =$E40/$E$41*G41 -> 4824.7389 | H40: =$E40/$E$41*H41 -> 5210.7181
B41: Total GMV | C41: n/a | D41: =SUM(D37:D40) -> 48754 | E41: =SUM(E37:E40) -> 49196.8 | F41: =E41*(1+Assumptions!C7) -> 53624.512 | G41: =F41*(1+Assumptions!D7) -> 58182.596 | H41: =G41*(1+Assumptions!E7) -> 62837.203
B42: of which: Quick Commerce (Integrated Verticals) GMV | C42: n/a | D42: 2904.7 | E42: 3432.3 | F42: =E42*(1+Assumptions!C22) -> 4118.76 | G42: =F42*(1+Assumptions!D22) -> 4818.9492 | H42: =G42*(1+Assumptions!E22) -> 5541.7916
B43: Asia+MENA+Europe+Americas GMV sums exactly to disclosed Total GMV in both FY2024A and FY2025A; Quick Commerce (Integrated Verticals) GMV is a memo subset already included within the four regions, not additive. FY2023A regional GMV split not separately disclosed. FY2026E-28E: Total GMV grown per the group LFL assumption (Assumptions sheet); regional split held at the FY2025A mix.
B45: Monetization — Total Segment Revenue as % of GMV ("take rate")
C46: FY2023A | D46: FY2024A | E46: FY2025A | F46: FY2026E | G46: FY2027E | H46: FY2028E
B47: Take rate | C47: n/a | D47: =D14/D41 -> 0.26246872 | E47: =E14/E41 -> 0.30090168 | F47: =F14/F41 -> 0.32015425 | G47: =G14/G41 -> 0.33603674 | H47: =H14/H41 -> 0.34983422

Sheet Income Statement
B2: Delivery Hero SE — Consolidated Income Statement
B3: EUR million unless noted. FY2021A-FY2025A as-reported IFRS actuals; FY2026E-FY2028E model forecast
B5: Revenue
C6: FY2021A | D6: FY2022A | E6: FY2023A | F6: FY2024A | G6: FY2025A | H6: FY2026E | I6: FY2027E | J6: FY2028E | K6: '21A-'25A CAGR | L6: '25A-'28E CAGR
B7: Total Segment Revenue (non-IFRS) | C7: n/a | D7: n/a | E7: ='Segment Detail'!C14 -> 11100 | F7: ='Segment Detail'!D14 -> 12796.4 | G7: ='Segment Detail'!E14 -> 14803.4 | H7: ='Segment Detail'!F14 -> 17168.116 | I7: ='Segment Detail'!G14 -> 19551.49 | J7: ='Segment Detail'!H14 -> 21982.604
B8: YoY growth % | C8: n/a | D8: n/a | E8: n/a | F8: =F7/E7-1 -> 0.15282883 | G8: =G7/F7-1 -> 0.15684099 | H8: =H7/G7-1 -> 0.15974138 | I8: =I7/H7-1 -> 0.13882561 | J8: =J7/I7-1 -> 0.1243442
B9: Revenue (IFRS, consolidated) | C9: 5856 | D9: 8577 | E9: 9942 | F9: 12295 | G9: 14060 | H9: =H7*Assumptions!C8 -> 16395.55 | I9: =I7*Assumptions!D8 -> 18671.673 | J9: =J7*Assumptions!E8 -> 20993.387
B10: YoY growth % | C10: n/a | D10: =D9/C9-1 -> 0.46465164 | E10: =E9/D9-1 -> 0.15914655 | F10: =F9/E9-1 -> 0.2366727 | G10: =G9/F9-1 -> 0.14355429 | H10: =H9/G9-1 -> 0.16611311 | I10: =I9/H9-1 -> 0.13882561 | J10: =J9/I9-1 -> 0.1243442 | K10: =(G9/C9)^(1/4)-1 -> 0.24478992 | L10: =(J9/G9)^(1/3)-1 -> 0.14296359
B12: Gross profit
C13: FY2021A | D13: FY2022A | E13: FY2023A | F13: FY2024A | G13: FY2025A | H13: FY2026E | I13: FY2027E | J13: FY2028E | K13: '21A-'25A CAGR | L13: '25A-'28E CAGR
B14: Gross profit | C14: 1258 | D14: 2232 | E14: 2973 | F14: 3329 | G14: 3433 | H14: =H9*Assumptions!C9 -> 4180.8653 | I14: =I9*Assumptions!D9 -> 4910.6499 | J14: =J9*Assumptions!E9 -> 5668.2144
B15: Cost of revenue (memo) | C15: =-(C9-C14) -> -4598 | D15: =-(D9-D14) -> -6345 | E15: =-(E9-E14) -> -6969 | F15: =-(F9-F14) -> -8966 | G15: =-(G9-G14) -> -10627 | H15: =-(H9-H14) -> -12214.685 | I15: =-(I9-I14) -> -13761.023 | J15: =-(J9-J14) -> -15325.172
B16: Gross margin, % of revenue | C16: =C14/C9 -> 0.2148224 | D16: =D14/D9 -> 0.26023085 | E16: =E14/E9 -> 0.2990344 | F16: =F14/F9 -> 0.27076047 | G16: =G14/G9 -> 0.24416785 | H16: =H14/H9 -> 0.255 | I16: =I14/I9 -> 0.263 | J16: =J14/J9 -> 0.27
B18: Adjusted EBITDA (company-defined non-IFRS metric)
C19: FY2021A | D19: FY2022A | E19: FY2023A | F19: FY2024A | G19: FY2025A | H19: FY2026E | I19: FY2027E | J19: FY2028E | K19: '21A-'25A CAGR | L19: '25A-'28E CAGR
B20: Adjusted EBITDA | C20: n/a | D20: n/a | E20: 253.3 | F20: 692.5 | G20: 906 | H20: =H7*Assumptions!C10 -> 935.6623 | I20: =I7*Assumptions!D10 -> 1212.1924 | J20: =J7*Assumptions!E10 -> 1538.7823
B21: YoY growth % | C21: n/a | D21: n/a | E21: n/a | F21: =F20/E20-1 -> 1.7339124 | G21: =G20/F20-1 -> 0.30830325 | H21: =H20/G20-1 -> 0.03273984 | I21: =I20/H20-1 -> 0.29554473 | J21: =J20/I20-1 -> 0.26942087
B22: Adj. EBITDA margin, % of Total Segment Revenue | C22: n/a | D22: n/a | E22: =E20/E7 -> 0.02281982 | F22: =F20/F7 -> 0.054116783 | G22: =G20/G7 -> 0.061202156 | H22: =H20/H7 -> 0.0545 | I22: =I20/I7 -> 0.062 | J22: =J20/J7 -> 0.07
B23: Adj. EBITDA margin, % of GMV | C23: n/a | D23: n/a | E23: n/a | F23: =F20/'Segment Detail'!D41 -> 0.014203963 | G23: =G20/'Segment Detail'!E41 -> 0.018415832 | H23: =H20/'Segment Detail'!F41 -> 0.017448407 | I23: =I20/'Segment Detail'!G41 -> 0.020834278 | J23: =J20/'Segment Detail'!H41 -> 0.024488395
B24: FY2025A Adjusted EBITDA disclosed only as "above EUR 900m" (+30% YoY) at time of modeling; EUR 906m used as a point estimate pending the audited FY2025 annual report figure. FY2026E guidance: EUR 910-960m (up-to-mid-single-digit % YoY growth) — implies a temporary margin dip vs FY2025A as the company continues to invest in Quick Commerce / new verticals, before margin re-expansion in FY2027E-28E.
B26: EBIT / Operating income (IFRS)
C27: FY2021A | D27: FY2022A | E27: FY2023A | F27: FY2024A | G27: FY2025A | H27: FY2026E | I27: FY2027E | J27: FY2028E | K27: '21A-'25A CAGR | L27: '25A-'28E CAGR
B28: Depreciation & amortization (forecast driver) | C28: n/a | D28: n/a | E28: n/a | F28: n/a | G28: n/a | H28: =-H9*Assumptions!C11 -> -344.30656 | I28: =-I9*Assumptions!D11 -> -373.43345 | J28: =-J9*Assumptions!E11 -> -398.87435
B29: EBIT / Operating income (IFRS, as reported) | C29: -1659 | D29: -1437 | E29: -707.4 | F29: -261.2 | G29: 93.7 | H29: =H20+H28 -> 591.35574 | I29: =I20+I28 -> 838.75891 | J29: =J20+J28 -> 1139.9079
B30: EBIT margin, % of revenue | C30: =C29/C9 -> -0.28329918 | D30: =D29/D9 -> -0.1675411 | E30: =E29/E9 -> -0.071152686 | F30: =F29/F9 -> -0.021244408 | G30: =G29/G9 -> 0.0066642959 | H30: =H29/H9 -> 0.036068063 | I30: =I29/I9 -> 0.044921466 | J30: =J29/J9 -> 0.054298429
B32: Net income build
C33: FY2021A | D33: FY2022A | E33: FY2023A | F33: FY2024A | G33: FY2025A | H33: FY2026E | I33: FY2027E | J33: FY2028E | K33: '21A-'25A CAGR | L33: '25A-'28E CAGR
B34: Net financial result (forecast assumption) | C34: n/a | D34: n/a | E34: n/a | F34: n/a | G34: n/a | H34: =Assumptions!C12 -> -230 | I34: =Assumptions!D12 -> -180 | J34: =Assumptions!E12 -> -140
B35: Earnings before tax (EBT) (forecast) | C35: n/a | D35: n/a | E35: n/a | F35: n/a | G35: n/a | H35: =H29+H34 -> 361.35574 | I35: =I29+I34 -> 658.75891 | J35: =J29+J34 -> 999.90793
B36: Income tax expense (forecast assumption) | C36: n/a | D36: n/a | E36: n/a | F36: n/a | G36: n/a | H36: =Assumptions!C13 -> -95 | I36: =Assumptions!D13 -> -110 | J36: =Assumptions!E13 -> -125
B37: Financial result, tax & non-controlling interests, net (historical bridge) | C37: =C38-C29 -> 535 | D37: =D38-D29 -> -1571 | E37: =E38-E29 -> -1590.6 | F37: =F38-F29 -> -621.2 | G37: =G38-G29 -> -876.6 | H37: n/a | I37: n/a | J37: n/a
B38: Net income (loss) | C38: -1124 | D38: -3008 | E38: -2298 | F38: -882.4 | G38: -782.9 | H38: =H35+H36 -> 266.35574 | I38: =I35+I36 -> 548.75891 | J38: =J35+J36 -> 874.90793
B39: Net margin, % of revenue | C39: =C38/C9 -> -0.19193989 | D39: =D38/D9 -> -0.35070537 | E39: =E38/E9 -> -0.23114062 | F39: =F38/F9 -> -0.071769012 | G39: =G38/G9 -> -0.055682788 | H39: =H38/H9 -> 0.016245611 | I39: =I38/I9 -> 0.029389917 | J39: =J38/J9 -> 0.041675407
B40: Diluted shares outstanding, million (memo) | C40: =C38/C41 -> 245.95186 | D40: =D38/D41 -> 266.66667 | E40: =E38/E41 -> 268.14469 | F40: =F38/F41 -> 284.64516 | G40: =G38/G41 -> 298.81679 | H40: =Assumptions!C14 -> 300 | I40: =Assumptions!D14 -> 301 | J40: =Assumptions!E14 -> 302
B41: EPS, diluted (EUR) | C41: -4.57 | D41: -11.28 | E41: -8.57 | F41: -3.1 | G41: -2.62 | H41: =H38/Assumptions!C14 -> 0.88785246 | I41: =I38/Assumptions!D14 -> 1.8231193 | J41: =J38/Assumptions!E14 -> 2.8970461
B43: Historical (FY2021A-FY2025A): Revenue, Gross profit, EBIT and Net income/EPS are as-reported IFRS consolidated figures. Granular interest/tax/NCI splits are not separately modeled for historical years; the "Financial result, tax & non-controlling interests, net" row is a computed bridge (Net income - EBIT), not a company-disclosed line. Forecast (FY2026E-FY2028E): built bottom-up from Adjusted EBITDA less an assumed D&A run-rate, plus assumption-driven net financial result and cash tax (Assumptions sheet); this simplification assumes no material one-off/non-underlying items going forward and excludes a separate non-controlling-interest adjustment.

Sheet Growth Dashboard
B2: Growth Analysis Dashboard
B3: All figures linked live to Income Statement / Segment Detail sheets — FY2023A-FY2028E
B5: Key growth KPIs
C6: FY2023A | D6: FY2024A | E6: FY2025A | F6: FY2026E | G6: FY2027E | H6: FY2028E
B7: Revenue (IFRS, consolidated) | C7: ='Income Statement'!E9 -> 9942 | D7: ='Income Statement'!F9 -> 12295 | E7: ='Income Statement'!G9 -> 14060 | F7: ='Income Statement'!H9 -> 16395.55 | G7: ='Income Statement'!I9 -> 18671.673 | H7: ='Income Statement'!J9 -> 20993.387
B8: Revenue growth, YoY % | C8: ='Income Statement'!E10 -> 0.15914655 | D8: ='Income Statement'!F10 -> 0.2366727 | E8: ='Income Statement'!G10 -> 0.14355429 | F8: ='Income Statement'!H10 -> 0.16611311 | G8: ='Income Statement'!I10 -> 0.13882561 | H8: ='Income Statement'!J10 -> 0.1243442
B9: Total Segment Revenue | C9: ='Income Statement'!E7 -> 11100 | D9: ='Income Statement'!F7 -> 12796.4 | E9: ='Income Statement'!G7 -> 14803.4 | F9: ='Income Statement'!H7 -> 17168.116 | G9: ='Income Statement'!I7 -> 19551.49 | H9: ='Income Statement'!J7 -> 21982.604
B10: GMV | C10: ='Segment Detail'!C41 -> n/a | D10: ='Segment Detail'!D41 -> 48754 | E10: ='Segment Detail'!E41 -> 49196.8 | F10: ='Segment Detail'!F41 -> 53624.512 | G10: ='Segment Detail'!G41 -> 58182.596 | H10: ='Segment Detail'!H41 -> 62837.203
B11: GMV growth, YoY % | C11: n/a | D11: n/a | E11: ='Segment Detail'!E41/'Segment Detail'!D41-1 -> 0.0090823317 | F11: =Assumptions!C7 -> 0.09 | G11: =Assumptions!D7 -> 0.085 | H11: =Assumptions!E7 -> 0.08
B12: Adjusted EBITDA | C12: ='Income Statement'!E20 -> 253.3 | D12: ='Income Statement'!F20 -> 692.5 | E12: ='Income Statement'!G20 -> 906 | F12: ='Income Statement'!H20 -> 935.6623 | G12: ='Income Statement'!I20 -> 1212.1924 | H12: ='Income Statement'!J20 -> 1538.7823
B13: Adj. EBITDA margin, % of Total Segment Revenue | C13: ='Income Statement'!E22 -> 0.02281982 | D13: ='Income Statement'!F22 -> 0.054116783 | E13: ='Income Statement'!G22 -> 0.061202156 | F13: ='Income Statement'!H22 -> 0.0545 | G13: ='Income Statement'!I22 -> 0.062 | H13: ='Income Statement'!J22 -> 0.07
B14: Net income (loss) | C14: ='Income Statement'!E38 -> -2298 | D14: ='Income Statement'!F38 -> -882.4 | E14: ='Income Statement'!G38 -> -782.9 | F14: ='Income Statement'!H38 -> 266.35574 | G14: ='Income Statement'!I38 -> 548.75891 | H14: ='Income Statement'!J38 -> 874.90793
B15: EPS, diluted (EUR) | C15: ='Income Statement'!E41 -> -8.57 | D15: ='Income Statement'!F41 -> -3.1 | E15: ='Income Statement'!G41 -> -2.62 | F15: ='Income Statement'!H41 -> 0.88785246 | G15: ='Income Statement'!I41 -> 1.8231193 | H15: ='Income Statement'!J41 -> 2.8970461
B17: CAGR summary
C18: FY23A-25A | D18: FY25A-28E
B19: Total Segment Revenue | C19: ='Segment Detail'!I14 -> 0.15483317 | D19: ='Segment Detail'!J14 -> 0.14087804
B20: Asia | C20: ='Segment Detail'!I7 -> 0.088389766 | D20: ='Segment Detail'!J7 -> 0.081648716
B21: MENA | C21: ='Segment Detail'!I8 -> 0.22209674 | D21: ='Segment Detail'!J8 -> 0.14493449
B22: Europe | C22: ='Segment Detail'!I9 -> 0.27794563 | D22: ='Segment Detail'!J9 -> 0.19621399
B23: Americas | C23: ='Segment Detail'!I10 -> 0.27458918 | D23: ='Segment Detail'!J10 -> 0.12326429
B24: Integrated Verticals | C24: ='Segment Detail'!I11 -> 0.21447721 | D24: ='Segment Detail'!J11 -> 0.17315388
B26: Revenue (IFRS) | C26: n/a | D26: ='Income Statement'!L10 -> 0.14296359
B27: memo: Revenue FY21A-25A CAGR | C27: ='Income Statement'!K10 -> 0.24478992
B67: Sources: Delivery Hero SE press releases & trading updates (Q4/FY2021-FY2025), FY2024 Annual Report, stockanalysis.com aggregated financials. FY2026-2028 = model forecast built on company FY2026 guidance (issued w/ Q4 2025 results, Feb-2026) and illustrative assumptions thereafter. All figures EUR million unless noted.
B68: Change any gold-shaded cell on the Assumptions sheet to re-run the FY2026E-FY2028E forecast across every sheet in this workbook.
