Workbook

Sheet Notes & Sources
A1: Apple Inc. (AAPL) — Income Statement Forecast, FY2026–FY2028 (Quarterly)
A2: Built 2026-08-17. All dollar figures in millions except per-share amounts; share counts in thousands.
A4: Scope
A5: Historical actuals cover FY2024 Q1 through FY2026 Q3 (11 quarters), sourced directly from Apple's condensed
A6: consolidated statements of operations as filed with the SEC / issued via Apple Newsroom press releases.
A7: Forecast periods are FY2026 Q4 (in progress at time of writing) through FY2028 Q4 (9 quarters).
A9: Sources (historical actuals)
A10: - Apple Inc. Form 10-Q, quarter ended Dec 27, 2025 (FY26 Q1) — sec.gov/Archives/edgar/data/320193
A11: - Apple Inc. Form 10-Q, quarter ended Mar 28, 2026 (FY26 Q2), 8-K Ex-99.1
A12: - Apple Inc. Form 10-Q, quarter ended Jun 27, 2026 (FY26 Q3), 8-K Ex-99.1
A13: - Apple Inc. FY2025 Form 10-K and Q4 FY25 press release (quarter/year ended Sep 27, 2025)
A14: - Apple quarterly press releases for FY24 Q1-Q4 and FY25 Q1-Q3 (apple.com/newsroom, Consolidated Financial Statements PDFs)
... A40: - Annual Summary: FY2024 - FY2028 fiscal-year roll-up, aggregated by formula from the quarterly sheet.

Sheet Assumptions
A1: Forecast Assumptions (FY2026 Q4 – FY2028 Q4)
A2: Editable drivers. Historical columns (B:L) are shown as 'Actual' — no assumptions apply.
B4: FY2024 Q1 | C4: FY2024 Q2 | D4: FY2024 Q3 | E4: FY2024 Q4 | F4: FY2025 Q1 | G4: FY2025 Q2 | H4: FY2025 Q3 | I4: FY2025 Q4 | J4: FY2026 Q1 | K4: FY2026 Q2 | L4: FY2026 Q3 | M4: FY2026 Q4 | N4: FY2027 Q1 | O4: FY2027 Q2 | P4: FY2027 Q3 | Q4: FY2027 Q4 | R4: FY2028 Q1 | S4: FY2028 Q2 | T4: FY2028 Q3 | U4: FY2028 Q4
B5: Dec 30, 2023 | C5: Mar 30, 2024 | D5: Jun 29, 2024 | E5: Sep 28, 2024 | F5: Dec 28, 2024 | G5: Mar 29, 2025 | H5: Jun 28, 2025 | I5: Sep 27, 2025 | J5: Dec 27, 2025 | K5: Mar 28, 2026 | L5: Jun 27, 2026 | M5: ~Sep 26, 2026 (E) | N5: ~Dec 2026 (E) | O5: ~Mar 2027 (E) | P5: ~Jun 2027 (E) | Q5: ~Sep 2027 (E) | R5: ~Dec 2027 (E) | S5: ~Mar 2028 (E) | T5: ~Jun 2028 (E) | U5: ~Sep 2028 (E)
B6: Actual | C6: Actual | D6: Actual | E6: Actual | F6: Actual | G6: Actual | H6: Actual | I6: Actual | J6: Actual | K6: Actual | L6: Actual | M6: Forecast | N6: Forecast | O6: Forecast | P6: Forecast | Q6: Forecast | R6: Forecast | S6: Forecast | T6: Forecast | U6: Forecast
A8: Products net sales — y/y growth % | B8: Actual | C8: Actual | D8: Actual | E8: Actual | F8: Actual | G8: Actual | H8: Actual | I8: Actual | J8: Actual | K8: Actual | L8: Actual | M8: 0.1 | N8: 0.07 | O8: 0.065 | P8: 0.06 | Q8: 0.06 | R8: 0.055 | S8: 0.05 | T8: 0.05 | U8: 0.05
A9: Services net sales — y/y growth % | B9: Actual | C9: Actual | D9: Actual | E9: Actual | F9: Actual | G9: Actual | H9: Actual | I9: Actual | J9: Actual | K9: Actual | L9: Actual | M9: 0.13 | N9: 0.12 | O9: 0.12 | P9: 0.11 | Q9: 0.11 | R9: 0.11 | S9: 0.1 | T9: 0.1 | U9: 0.1
A11: Products gross margin % | B11: Actual | C11: Actual | D11: Actual | E11: Actual | F11: Actual | G11: Actual | H11: Actual | I11: Actual | J11: Actual | K11: Actual | L11: Actual | M11: 0.39 | N11: 0.393 | O11: 0.393 | P11: 0.393 | Q11: 0.393 | R11: 0.396 | S11: 0.396 | T11: 0.396 | U11: 0.396
A12: Services gross margin % | B12: Actual | C12: Actual | D12: Actual | E12: Actual | F12: Actual | G12: Actual | H12: Actual | I12: Actual | J12: Actual | K12: Actual | L12: Actual | M12: 0.76 | N12: 0.76 | O12: 0.762 | P12: 0.762 | Q12: 0.762 | R12: 0.765 | S12: 0.765 | T12: 0.765 | U12: 0.765
A14: R&D expense — % of total net sales | B14: Actual | C14: Actual | D14: Actual | E14: Actual | F14: Actual | G14: Actual | H14: Actual | I14: Actual | J14: Actual | K14: Actual | L14: Actual | M14: 0.088 | N14: 0.076 | O14: 0.102 | P14: 0.106 | Q14: 0.087 | R14: 0.075 | S14: 0.101 | T14: 0.105 | U14: 0.086
A15: SG&A expense — % of total net sales | B15: Actual | C15: Actual | D15: Actual | E15: Actual | F15: Actual | G15: Actual | H15: Actual | I15: Actual | J15: Actual | K15: Actual | L15: Actual | M15: 0.068 | N15: 0.052 | O15: 0.066 | P15: 0.066 | Q15: 0.067 | R15: 0.051 | S15: 0.065 | T15: 0.065 | U15: 0.066
A17: Other income/(expense), net ($M) | B17: Actual | C17: Actual | D17: Actual | E17: Actual | F17: Actual | G17: Actual | H17: Actual | I17: Actual | J17: Actual | K17: Actual | L17: Actual | M17: 100 | N17: 150 | O17: 100 | P17: 100 | Q17: 150 | R17: 150 | S17: 100 | T17: 100 | U17: 150
A19: Effective tax rate % | B19: Actual | C19: Actual | D19: Actual | E19: Actual | F19: Actual | G19: Actual | H19: Actual | I19: Actual | J19: Actual | K19: Actual | L19: Actual | M19: 0.175 | N19: 0.175 | O19: 0.175 | P19: 0.175 | Q19: 0.175 | R19: 0.176 | S19: 0.176 | T19: 0.176 | U19: 0.176
A21: Diluted shares outstanding — y/y change % | B21: Actual | C21: Actual | D21: Actual | E21: Actual | F21: Actual | G21: Actual | H21: Actual | I21: Actual | J21: Actual | K21: Actual | L21: Actual | M21: -0.018 | N21: -0.016 | O21: -0.016 | P21: -0.015 | Q21: -0.015 | R21: -0.013 | S21: -0.013 | T21: -0.012 | U21: -0.012
A22: Basic / diluted shares ratio | B22: Actual | C22: Actual | D22: Actual | E22: Actual | F22: Actual | G22: Actual | H22: Actual | I22: Actual | J22: Actual | K22: Actual | L22: Actual | M22: 0.9958 | N22: 0.9958 | O22: 0.9958 | P22: 0.9958 | Q22: 0.9958 | R22: 0.9958 | S22: 0.9958 | T22: 0.9958 | U22: 0.9958

Sheet Quarterly Income Statement
A1: Apple Inc. — Quarterly Income Statement
A2: $ in millions except per-share amounts; shares in thousands. FY2024 Q1 - FY2026 Q3 actual; FY2026 Q4 - FY2028 Q4 forecast.
B4: FY2024 Q1 | C4: FY2024 Q2 | D4: FY2024 Q3 | E4: FY2024 Q4 | F4: FY2025 Q1 | G4: FY2025 Q2 | H4: FY2025 Q3 | I4: FY2025 Q4 | J4: FY2026 Q1 | K4: FY2026 Q2 | L4: FY2026 Q3 | M4: FY2026 Q4 | N4: FY2027 Q1 | O4: FY2027 Q2 | P4: FY2027 Q3 | Q4: FY2027 Q4 | R4: FY2028 Q1 | S4: FY2028 Q2 | T4: FY2028 Q3 | U4: FY2028 Q4
B5: Dec 30, 2023 | C5: Mar 30, 2024 | D5: Jun 29, 2024 | E5: Sep 28, 2024 | F5: Dec 28, 2024 | G5: Mar 29, 2025 | H5: Jun 28, 2025 | I5: Sep 27, 2025 | J5: Dec 27, 2025 | K5: Mar 28, 2026 | L5: Jun 27, 2026 | M5: ~Sep 26, 2026 (E) | N5: ~Dec 2026 (E) | O5: ~Mar 2027 (E) | P5: ~Jun 2027 (E) | Q5: ~Sep 2027 (E) | R5: ~Dec 2027 (E) | S5: ~Mar 2028 (E) | T5: ~Jun 2028 (E) | U5: ~Sep 2028 (E)
B6: Actual | C6: Actual | D6: Actual | E6: Actual | F6: Actual | G6: Actual | H6: Actual | I6: Actual | J6: Actual | K6: Actual | L6: Actual | M6: Forecast | N6: Forecast | O6: Forecast | P6: Forecast | Q6: Forecast | R6: Forecast | S6: Forecast | T6: Forecast | U6: Forecast
A7: NET SALES
A8: Net sales — Products | B8: 96458 | C8: 66886 | D8: 61564 | E8: 69958 | F8: 97960 | G8: 68714 | H8: 66613 | I8: 73716 | J8: 113743 | K8: 80208 | L8: 78678 | M8: =I8*(1+Assumptions!M8) -> 81087.6 | N8: =J8*(1+Assumptions!N8) -> 121705.01 | O8: =K8*(1+Assumptions!O8) -> 85421.52 | P8: =L8*(1+Assumptions!P8) -> 83398.68 | Q8: =M8*(1+Assumptions!Q8) -> 85952.856 | R8: =N8*(1+Assumptions!R8) -> 128398.79 | S8: =O8*(1+Assumptions!S8) -> 89692.596 | T8: =P8*(1+Assumptions!T8) -> 87568.614 | U8: =Q8*(1+Assumptions!U8) -> 90250.499
A9: Net sales — Services | B9: 23117 | C9: 23867 | D9: 24213 | E9: 24972 | F9: 26340 | G9: 26645 | H9: 27423 | I9: 28750 | J9: 30013 | K9: 30976 | L9: 30739 | M9: =I9*(1+Assumptions!M9) -> 32487.5 | N9: =J9*(1+Assumptions!N9) -> 33614.56 | O9: =K9*(1+Assumptions!O9) -> 34693.12 | P9: =L9*(1+Assumptions!P9) -> 34120.29 | Q9: =M9*(1+Assumptions!Q9) -> 36061.125 | R9: =N9*(1+Assumptions!R9) -> 37312.162 | S9: =O9*(1+Assumptions!S9) -> 38162.432 | T9: =P9*(1+Assumptions!T9) -> 37532.319 | U9: =Q9*(1+Assumptions!U9) -> 39667.238
A10: Total net sales | B10: =B8+B9 -> 119575 | C10: =C8+C9 -> 90753 | D10: =D8+D9 -> 85777 | E10: =E8+E9 -> 94930 | F10: =F8+F9 -> 124300 | G10: =G8+G9 -> 95359 | H10: =H8+H9 -> 94036 | I10: =I8+I9 -> 102466 | ... U10: =U8+U9 -> 129917.74
A11: y/y growth % | F11: =F10/B10-1 -> 0.039514949 | G11: =G10/C10-1 -> 0.050753143 | H11: =H10/D10-1 -> 0.096284552 | I11: =I10/E10-1 -> 0.07938481 | J11: =J10/F10-1 -> 0.15652454 | K11: =K10/G10-1 -> 0.16595182 | L11: =L10/H10-1 -> 0.16356502 | M11: =M10/I10-1 -> 0.10841743 | ... U11: =U10/Q10-1 -> 0.064777456
A12: COST OF SALES
A13: Cost of sales — Products | B13: 58440 | C13: 42424 | D13: 39803 | E13: 44566 | F13: 59447 | G13: 44030 | H13: 43620 | I13: 47019 | J13: 67478 | K13: 49179 | L13: 47153 | M13: =M8*(1-Assumptions!M11) -> 49463.436 | N13: =N8*(1-Assumptions!N11) -> 73874.941 | O13: =O8*(1-Assumptions!O11) -> 51850.863 | P13: =P8*(1-Assumptions!P11) -> 50622.999 | Q13: =Q8*(1-Assumptions!Q11) -> 52173.384 | R13: =R8*(1-Assumptions!R11) -> 77552.866 | S13: =S8*(1-Assumptions!S11) -> 54174.328 | T13: =T8*(1-Assumptions!T11) -> 52891.443 | U13: =U8*(1-Assumptions!U11) -> 54511.301
A14: Cost of sales — Services | B14: 6280 | C14: 6058 | D14: 6296 | E14: 6485 | F14: 6578 | G14: 6462 | H14: 6698 | I14: 7106 | J14: 7047 | K14: 7224 | L14: 7494 | M14: =M9*(1-Assumptions!M12) -> 7797 | N14: =N9*(1-Assumptions!N12) -> 8067.4944 | O14: =O9*(1-Assumptions!O12) -> 8256.9626 | P14: =P9*(1-Assumptions!P12) -> 8120.629 | Q14: =Q9*(1-Assumptions!Q12) -> 8582.5477 | R14: =R9*(1-Assumptions!R12) -> 8768.358 | S14: =S9*(1-Assumptions!S12) -> 8968.1715 | T14: =T9*(1-Assumptions!T12) -> 8820.095 | U14: =U9*(1-Assumptions!U12) -> 9321.8008
A15: Total cost of sales | B15: =B13+B14 -> 64720 | C15: =C13+C14 -> 48482 | D15: =D13+D14 -> 46099 | E15: =E13+E14 -> 51051 | F15: =F13+F14 -> 66025 | G15: =G13+G14 -> 50492 | H15: =H13+H14 -> 50318 | I15: =I13+I14 -> 54125 | ... U15: =U13+U14 -> 63833.102
A16: GROSS MARGIN
A17: Gross margin ($) | B17: =B10-B15 -> 54855 | C17: =C10-C15 -> 42271 | D17: =D10-D15 -> 39678 | E17: =E10-E15 -> 43879 | F17: =F10-F15 -> 58275 | G17: =G10-G15 -> 44867 | H17: =H10-H15 -> 43718 | I17: =I10-I15 -> 48341 | ... U17: =U10-U15 -> 66084.634
A18: Gross margin % — Products | B18: =(B8-B13)/B8 -> 0.39414045 | C18: =(C8-C13)/C8 -> 0.36572676 | D18: =(D8-D13)/D8 -> 0.35346956 | E18: =(E8-E13)/E8 -> 0.36296063 | F18: =(F8-F13)/F8 -> 0.39315027 | G18: =(G8-G13)/G8 -> 0.3592281 | H18: =(H8-H13)/H8 -> 0.34517286 | I18: =(I8-I13)/I8 -> 0.36216018 | ... U18: =(U8-U13)/U8 -> 0.396
A19: Gross margin % — Services | B19: =(B9-B14)/B9 -> 0.72833845 | C19: =(C9-C14)/C9 -> 0.74617673 | D19: =(D9-D14)/D9 -> 0.73997439 | E19: =(E9-E14)/E9 -> 0.74030915 | F19: =(F9-F14)/F9 -> 0.75026576 | G19: =(G9-G14)/G9 -> 0.75747795 | H19: =(H9-H14)/H9 -> 0.75575247 | I19: =(I9-I14)/I9 -> 0.75283478 | ... U19: =(U9-U14)/U9 -> 0.765
A20: Gross margin % — Total | B20: =B17/B10 -> 0.45874974 | C20: =C17/C10 -> 0.46578075 | D20: =D17/D10 -> 0.46257155 | E20: =E17/E10 -> 0.4622248 | F20: =F17/F10 -> 0.46882542 | G20: =G17/G10 -> 0.47050619 | H20: =H17/H10 -> 0.46490706 | I20: =I17/I10 -> 0.471776 | ... U20: =U17/U10 -> 0.50866522
A21: OPERATING EXPENSES
A22: Research and development | B22: 7696 | C22: 7903 | D22: 8006 | E22: 7765 | F22: 8268 | G22: 8550 | H22: 8866 | I22: 8866 | J22: 10887 | K22: 11419 | L22: 11729 | M22: =M10*Assumptions!M14 -> 9994.6088 | N22: =N10*Assumptions!N14 -> 11804.287 | O22: =O10*Assumptions!O14 -> 12251.693 | P22: =P10*Assumptions!P14 -> 12457.011 | Q22: =Q10*Assumptions!Q14 -> 10615.216 | R22: =R10*Assumptions!R14 -> 12428.321 | S22: =S10*Assumptions!S14 -> 12913.358 | T22: =T10*Assumptions!T14 -> 13135.598 | U22: =U10*Assumptions!U14 -> 11172.925
A23: Selling, general and administrative | B23: 6786 | C23: 6468 | D23: 6320 | E23: 6523 | F23: 7175 | G23: 6728 | H23: 6650 | I23: 7048 | J23: 7492 | K23: 7477 | L23: 7346 | M23: =M10*Assumptions!M15 -> 7723.1068 | N23: =N10*Assumptions!N15 -> 8076.6176 | O23: =O10*Assumptions!O15 -> 7927.5662 | P23: =P10*Assumptions!P15 -> 7756.252 | Q23: =Q10*Assumptions!Q15 -> 8174.9367 | R23: =R10*Assumptions!R15 -> 8451.2583 | S23: =S10*Assumptions!S15 -> 8310.5768 | T23: =T10*Assumptions!T15 -> 8131.5606 | U23: =U10*Assumptions!U15 -> 8574.5706
A24: Total operating expenses | B24: =B22+B23 -> 14482 | C24: =C22+C23 -> 14371 | D24: =D22+D23 -> 14326 | E24: =E22+E23 -> 14288 | F24: =F22+F23 -> 15443 | G24: =G22+G23 -> 15278 | H24: =H22+H23 -> 15516 | I24: =I22+I23 -> 15914 | ... U24: =U22+U23 -> 19747.496
A25: OPERATING INCOME
A26: Operating income | B26: =B17-B24 -> 40373 | C26: =C17-C24 -> 27900 | D26: =D17-D24 -> 25352 | E26: =E17-E24 -> 29591 | F26: =F17-F24 -> 42832 | G26: =G17-G24 -> 29589 | H26: =H17-H24 -> 28202 | I26: =I17-I24 -> 32427 | ... U26: =U17-U24 -> 46337.138
A27: Operating margin % | B27: =B26/B10 -> 0.33763747 | C27: =C26/C10 -> 0.30742785 | D27: =D26/D10 -> 0.29555708 | E27: =E26/E10 -> 0.31171389 | F27: =F26/F10 -> 0.34458568 | G27: =G26/G10 -> 0.31029059 | H27: =H26/H10 -> 0.29990642 | I27: =I26/I10 -> 0.31646595 | ... U27: =U26/U10 -> 0.35666522
A28: OTHER INCOME / TAXES / NET INCOME
A29: Other income/(expense), net | B29: -50 | C29: 158 | D29: 142 | E29: 19 | F29: -248 | G29: -279 | H29: -171 | I29: 377 | J29: 150 | K29: -52 | L29: 572 | M29: =Assumptions!M17 -> 100 | N29: =Assumptions!N17 -> 150 | O29: =Assumptions!O17 -> 100 | P29: =Assumptions!P17 -> 100 | Q29: =Assumptions!Q17 -> 150 | R29: =Assumptions!R17 -> 150 | S29: =Assumptions!S17 -> 100 | T29: =Assumptions!T17 -> 100 | U29: =Assumptions!U17 -> 150
A30: Income before provision for income taxes | B30: =B26+B29 -> 40323 | C30: =C26+C29 -> 28058 | D30: =D26+D29 -> 25494 | E30: =E26+E29 -> 29610 | F30: =F26+F29 -> 42584 | G30: =G26+G29 -> 29310 | H30: =H26+H29 -> 28031 | I30: =I26+I29 -> 32804 | ... U30: =U26+U29 -> 46487.138
A31: Provision for income taxes | B31: 6407 | C31: 4422 | D31: 4046 | E31: 14874 | F31: 6254 | G31: 4530 | H31: 4597 | I31: 5338 | J31: 8905 | K31: 6255 | L31: 6478 | M31: =M30*Assumptions!M19 -> 6771.966 | N31: =N30*Assumptions!N19 -> 9388.0902 | O31: =O30*Assumptions!O19 -> 6987.3222 | P31: =P30*Assumptions!P19 -> 6765.8639 | Q31: =Q30*Assumptions!Q19 -> 7458.1319 | R31: =R30*Assumptions!R19 -> 10324.185 | S31: =S30*Assumptions!S19 -> 7671.5925 | T31: =T30*Assumptions!T19 -> 7431.1136 | U31: =U30*Assumptions!U19 -> 8181.7363
A32: Effective tax rate % | B32: =B31/B30 -> 0.15889195 | C32: =C31/C30 -> 0.15760211 | D32: =D31/D30 -> 0.15870401 | E32: =E31/E30 -> 0.50233029 | F32: =F31/F30 -> 0.14686267 | G32: =G31/G30 -> 0.15455476 | H32: =H31/H30 -> 0.163997 | I32: =I31/I30 -> 0.16272406 | ... U32: =U31/U30 -> 0.176
A33: Net income | B33: =B30-B31 -> 33916 | C33: =C30-C31 -> 23636 | D33: =D30-D31 -> 21448 | E33: =E30-E31 -> 14736 | F33: =F30-F31 -> 36330 | G33: =G30-G31 -> 24780 | H33: =H30-H31 -> 23434 | I33: =I30-I31 -> 27466 | ... U33: =U30-U31 -> 38305.402
A34: Net margin % | B34: =B33/B10 -> 0.28363788 | C34: =C33/C10 -> 0.26044318 | D34: =D33/D10 -> 0.25004372 | E34: =E33/E10 -> 0.15523017 | F34: =F33/F10 -> 0.29227675 | G34: =G33/G10 -> 0.25986011 | H34: =H33/H10 -> 0.24920243 | I34: =I33/I10 -> 0.26804989 | ... U34: =U33/U10 -> 0.29484351
A35: y/y growth % | F35: =F33/B33-1 -> 0.071175846 | G35: =G33/C33-1 -> 0.048400745 | H35: =H33/D33-1 -> 0.092596046 | I35: =I33/E33-1 -> 0.86387079 | J35: =J33/F33-1 -> 0.15873933 | K35: =K33/G33-1 -> 0.19362389 | L35: =L33/H33-1 -> 0.27118716 | M35: =M33/I33-1 -> 0.16234553 | ... U35: =U33/Q33-1 -> 0.08946696
A36: PER-SHARE DATA
A37: Earnings per share — Basic | B37: =B33*1000/B40 -> 2.1867517 | C37: =C33*1000/C40 -> 1.5342218 | D37: =D33*1000/D40 -> 1.4029744 | E37: =E33*1000/E40 -> 0.97126349 | F37: =F33*1000/F40 -> 2.4088758 | G37: =G33*1000/G40 -> 1.652652 | H37: =H33*1000/H40 -> 1.5724471 | I37: =I33*1000/I40 -> 1.8538934 | ... U37: =U33*1000/U40 -> 2.7080643
A38: Earnings per share — Diluted | B38: =B33*1000/B41 -> 2.1773629 | C38: =C33*1000/C41 -> 1.5283831 | D38: =D33*1000/D41 -> 1.39743 | E38: =E33*1000/E41 -> 0.96674815 | F38: =F33*1000/F41 -> 2.3978829 | G38: =G33*1000/G41 -> 1.6458409 | H38: =H33*1000/H41 -> 1.5676826 | I38: =I33*1000/I41 -> 1.8478688 | ... U38: =U33*1000/U41 -> 2.6966904
A40: Shares used in computing EPS — Basic | B40: 15509763 | C40: 15405856 | D40: 15287521 | E40: 15171990 | F40: 15081724 | G40: 14994082 | H40: 14902886 | I40: 14815307 | J40: 14748158 | K40: 14673278 | L40: 14656110 | M40: =M41*Assumptions!M22 -> 14534761 | N40: =N41*Assumptions!N22 -> 14512182 | O40: =O41*Assumptions!O22 -> 14429400 | P40: =P41*Assumptions!P22 -> 14433081 | Q40: =Q41*Assumptions!Q22 -> 14316739 | R40: =R41*Assumptions!R22 -> 14323524 | S40: =S41*Assumptions!S22 -> 14241818 | T40: =T41*Assumptions!T22 -> 14259884 | U40: =U41*Assumptions!U22 -> 14144938
A41: Shares used in computing EPS — Diluted | B41: 15576641 | C41: 15464709 | D41: 15348175 | E41: 15242853 | F41: 15150865 | G41: 15056133 | H41: 14948179 | I41: 14863609 | J41: 14810356 | K41: 14725873 | L41: 14714676 | M41: =I41*(1+Assumptions!M21) -> 14596064 | N41: =J41*(1+Assumptions!N21) -> 14573390 | O41: =K41*(1+Assumptions!O21) -> 14490259 | P41: =L41*(1+Assumptions!P21) -> 14493956 | Q41: =M41*(1+Assumptions!Q21) -> 14377123 | R41: =N41*(1+Assumptions!R21) -> 14383936 | S41: =O41*(1+Assumptions!S21) -> 14301886 | T41: =P41*(1+Assumptions!T21) -> 14320028 | U41: =Q41*(1+Assumptions!U21) -> 14204598

Sheet Annual Summary
A1: Apple Inc. — Annual Income Statement Summary
A2: $ in millions except per-share amounts; shares in thousands. FY2024-FY2025 actual; FY2026 partial actual (Q1-Q3) + Q4 forecast; FY2027-FY2028 forecast.
B4: FY2024 | C4: FY2025 | D4: FY2026 | E4: FY2027 | F4: FY2028
B5: Actual | C5: Actual | D5: Actual (9mo) + Forecast (Q4) | E5: Forecast | F5: Forecast
A6: NET SALES
A7: Net sales — Products | B7: ='Quarterly Income Statement'!B8+'Quarterly Income Statement'!C8+'Quarterly Income Statement'!D8+'Quarterly Income Statement'!E8 -> 294866 | C7: ='Quarterly Income Statement'!F8+'Quarterly Income Statement'!G8+'Quarterly Income Statement'!H8+'Quarterly Income Statement'!I8 -> 307003 | D7: ='Quarterly Income Statement'!J8+'Quarterly Income Statement'!K8+'Quarterly Income Statement'!L8+'Quarterly Income Statement'!M8 -> 353716.6 | E7: ='Quarterly Income Statement'!N8+'Quarterly Income Statement'!O8+'Quarterly Income Statement'!P8+'Quarterly Income Statement'!Q8 -> 376478.07 | F7: ='Quarterly Income Statement'!R8+'Quarterly Income Statement'!S8+'Quarterly Income Statement'!T8+'Quarterly Income Statement'!U8 -> 395910.49
A8: Net sales — Services | B8: ='Quarterly Income Statement'!B9+'Quarterly Income Statement'!C9+'Quarterly Income Statement'!D9+'Quarterly Income Statement'!E9 -> 96169 | C8: ='Quarterly Income Statement'!F9+'Quarterly Income Statement'!G9+'Quarterly Income Statement'!H9+'Quarterly Income Statement'!I9 -> 109158 | D8: ='Quarterly Income Statement'!J9+'Quarterly Income Statement'!K9+'Quarterly Income Statement'!L9+'Quarterly Income Statement'!M9 -> 124215.5 | E8: ='Quarterly Income Statement'!N9+'Quarterly Income Statement'!O9+'Quarterly Income Statement'!P9+'Quarterly Income Statement'!Q9 -> 138489.1 | F8: ='Quarterly Income Statement'!R9+'Quarterly Income Statement'!S9+'Quarterly Income Statement'!T9+'Quarterly Income Statement'!U9 -> 152674.15
A9: Total net sales | B9: =B7+B8 -> 391035 | C9: =C7+C8 -> 416161 | D9: =D7+D8 -> 477932.1 | E9: =E7+E8 -> 514967.16 | F9: =F7+F8 -> 548584.64
A10: y/y growth % | C10: =C9/B9-1 -> 0.064255118 | D10: =D9/C9-1 -> 0.14843078 | E10: =E9/D9-1 -> 0.077490215 | F10: =F9/E9-1 -> 0.06528083
A11: COST OF SALES
A12: Cost of sales — Products | B12: ='Quarterly Income Statement'!B13+'Quarterly Income Statement'!C13+'Quarterly Income Statement'!D13+'Quarterly Income Statement'!E13 -> 185233 | C12: ='Quarterly Income Statement'!F13+'Quarterly Income Statement'!G13+'Quarterly Income Statement'!H13+'Quarterly Income Statement'!I13 -> 194116 | D12: ='Quarterly Income Statement'!J13+'Quarterly Income Statement'!K13+'Quarterly Income Statement'!L13+'Quarterly Income Statement'!M13 -> 213273.44 | E12: ='Quarterly Income Statement'!N13+'Quarterly Income Statement'!O13+'Quarterly Income Statement'!P13+'Quarterly Income Statement'!Q13 -> 228522.19 | F12: ='Quarterly Income Statement'!R13+'Quarterly Income Statement'!S13+'Quarterly Income Statement'!T13+'Quarterly Income Statement'!U13 -> 239129.94
A13: Cost of sales — Services | B13: ='Quarterly Income Statement'!B14+'Quarterly Income Statement'!C14+'Quarterly Income Statement'!D14+'Quarterly Income Statement'!E14 -> 25119 | C13: ='Quarterly Income Statement'!F14+'Quarterly Income Statement'!G14+'Quarterly Income Statement'!H14+'Quarterly Income Statement'!I14 -> 26844 | D13: ='Quarterly Income Statement'!J14+'Quarterly Income Statement'!K14+'Quarterly Income Statement'!L14+'Quarterly Income Statement'!M14 -> 29562 | E13: ='Quarterly Income Statement'!N14+'Quarterly Income Statement'!O14+'Quarterly Income Statement'!P14+'Quarterly Income Statement'!Q14 -> 33027.634 | F13: ='Quarterly Income Statement'!R14+'Quarterly Income Statement'!S14+'Quarterly Income Statement'!T14+'Quarterly Income Statement'!U14 -> 35878.425
A14: Total cost of sales | B14: =B12+B13 -> 210352 | C14: =C12+C13 -> 220960 | D14: =D12+D13 -> 242835.44 | E14: =E12+E13 -> 261549.82 | F14: =F12+F13 -> 275008.36
A15: GROSS MARGIN
A16: Gross margin ($) | B16: =B9-B14 -> 180683 | C16: =C9-C14 -> 195201 | D16: =D9-D14 -> 235096.66 | E16: =E9-E14 -> 253417.34 | F16: =F9-F14 -> 273576.28
A17: Gross margin % — Products | B17: =(B7-B12)/B7 -> 0.37180618 | C17: =(C7-C12)/C7 -> 0.3677065 | D17: =(D7-D12)/D7 -> 0.39704997 | E17: =(E7-E12)/E7 -> 0.393 | F17: =(F7-F12)/F7 -> 0.396
A18: Gross margin % — Services | B18: =(B8-B13)/B8 -> 0.73880356 | C18: =(C8-C13)/C8 -> 0.75408124 | D18: =(D8-D13)/D8 -> 0.76201038 | E18: =(E8-E13)/E8 -> 0.76151455 | F18: =(F8-F13)/F8 -> 0.765
A19: Gross margin % — Total | B19: =B16/B9 -> 0.4620635 | C19: =C16/C9 -> 0.46905164 | D19: =D16/D9 -> 0.4919039 | E19: =E16/E9 -> 0.49210389 | F19: =F16/F9 -> 0.49869475
A20: OPERATING EXPENSES
A21: Research and development | B21: ='Quarterly Income Statement'!B22+'Quarterly Income Statement'!C22+'Quarterly Income Statement'!D22+'Quarterly Income Statement'!E22 -> 31370 | C21: ='Quarterly Income Statement'!F22+'Quarterly Income Statement'!G22+'Quarterly Income Statement'!H22+'Quarterly Income Statement'!I22 -> 34550 | D21: ='Quarterly Income Statement'!J22+'Quarterly Income Statement'!K22+'Quarterly Income Statement'!L22+'Quarterly Income Statement'!M22 -> 44029.609 | E21: ='Quarterly Income Statement'!N22+'Quarterly Income Statement'!O22+'Quarterly Income Statement'!P22+'Quarterly Income Statement'!Q22 -> 47128.208 | F21: ='Quarterly Income Statement'!R22+'Quarterly Income Statement'!S22+'Quarterly Income Statement'!T22+'Quarterly Income Statement'!U22 -> 49650.202
A22: Selling, general and administrative | B22: ='Quarterly Income Statement'!B23+'Quarterly Income Statement'!C23+'Quarterly Income Statement'!D23+'Quarterly Income Statement'!E23 -> 26097 | C22: ='Quarterly Income Statement'!F23+'Quarterly Income Statement'!G23+'Quarterly Income Statement'!H23+'Quarterly Income Statement'!I23 -> 27601 | D22: ='Quarterly Income Statement'!J23+'Quarterly Income Statement'!K23+'Quarterly Income Statement'!L23+'Quarterly Income Statement'!M23 -> 30038.107 | E22: ='Quarterly Income Statement'!N23+'Quarterly Income Statement'!O23+'Quarterly Income Statement'!P23+'Quarterly Income Statement'!Q23 -> 31935.373 | F22: ='Quarterly Income Statement'!R23+'Quarterly Income Statement'!S23+'Quarterly Income Statement'!T23+'Quarterly Income Statement'!U23 -> 33467.966
A23: Total operating expenses | B23: =B21+B22 -> 57467 | C23: =C21+C22 -> 62151 | D23: =D21+D22 -> 74067.716 | E23: =E21+E22 -> 79063.58 | F23: =F21+F22 -> 83118.169
A24: OPERATING INCOME
A25: Operating income | B25: =B16-B23 -> 123216 | C25: =C16-C23 -> 133050 | D25: =D16-D23 -> 161028.95 | E25: =E16-E23 -> 174353.76 | F25: =F16-F23 -> 190458.11
A26: Operating margin % | B26: =B25/B9 -> 0.31510223 | C26: =C25/C9 -> 0.319708 | D26: =D25/D9 -> 0.33692851 | E26: =E25/E9 -> 0.33857258 | F26: =F25/F9 -> 0.3471809
A27: OTHER INCOME / TAXES / NET INCOME
A28: Other income/(expense), net | B28: ='Quarterly Income Statement'!B29+'Quarterly Income Statement'!C29+'Quarterly Income Statement'!D29+'Quarterly Income Statement'!E29 -> 269 | C28: ='Quarterly Income Statement'!F29+'Quarterly Income Statement'!G29+'Quarterly Income Statement'!H29+'Quarterly Income Statement'!I29 -> -321 | D28: ='Quarterly Income Statement'!J29+'Quarterly Income Statement'!K29+'Quarterly Income Statement'!L29+'Quarterly Income Statement'!M29 -> 770 | E28: ='Quarterly Income Statement'!N29+'Quarterly Income Statement'!O29+'Quarterly Income Statement'!P29+'Quarterly Income Statement'!Q29 -> 500 | F28: ='Quarterly Income Statement'!R29+'Quarterly Income Statement'!S29+'Quarterly Income Statement'!T29+'Quarterly Income Statement'!U29 -> 500
A29: Income before provision for income taxes | B29: =B25+B28 -> 123485 | C29: =C25+C28 -> 132729 | D29: =D25+D28 -> 161798.95 | E29: =E25+E28 -> 174853.76 | F29: =F25+F28 -> 190958.11
A30: Provision for income taxes | B30: ='Quarterly Income Statement'!B31+'Quarterly Income Statement'!C31+'Quarterly Income Statement'!D31+'Quarterly Income Statement'!E31 -> 29749 | C30: ='Quarterly Income Statement'!F31+'Quarterly Income Statement'!G31+'Quarterly Income Statement'!H31+'Quarterly Income Statement'!I31 -> 20719 | D30: ='Quarterly Income Statement'!J31+'Quarterly Income Statement'!K31+'Quarterly Income Statement'!L31+'Quarterly Income Statement'!M31 -> 28409.966 | E30: ='Quarterly Income Statement'!N31+'Quarterly Income Statement'!O31+'Quarterly Income Statement'!P31+'Quarterly Income Statement'!Q31 -> 30599.408 | F30: ='Quarterly Income Statement'!R31+'Quarterly Income Statement'!S31+'Quarterly Income Statement'!T31+'Quarterly Income Statement'!U31 -> 33608.628
A31: Effective tax rate % | B31: =B30/B29 -> 0.24091185 | C31: =C30/C29 -> 0.15610002 | D31: =D30/D29 -> 0.17558808 | E31: =E30/E29 -> 0.175 | F31: =F30/F29 -> 0.176
A32: Net income | B32: =B29-B30 -> 93736 | C32: =C29-C30 -> 112010 | D32: =D29-D30 -> 133388.98 | E32: =E29-E30 -> 144254.35 | F32: =F29-F30 -> 157349.48
A33: Net margin % | B33: =B32/B9 -> 0.23971256 | C33: =C32/C9 -> 0.26915064 | D33: =D32/D9 -> 0.27909609 | E33: =E32/E9 -> 0.2801234 | F33: =F32/F9 -> 0.28682809
A34: y/y growth % | C34: =C32/B32-1 -> 0.19495178 | D34: =D32/C32-1 -> 0.19086673 | E34: =E32/D32-1 -> 0.08145628 | F34: =F32/E32-1 -> 0.09077807
A35: PER-SHARE DATA
A36: Earnings per share — Basic | B36: =B32*1000/B39 -> 6.1090543 | C36: =C32*1000/C39 -> 7.4930596 | D36: =D32*1000/D39 -> 9.1031382 | E36: =E32*1000/E39 -> 10.001792 | F36: =F32*1000/F39 -> 11.047852
A37: Earnings per share — Diluted | B37: =B32*1000/B40 -> 6.0835556 | C37: =C32*1000/C40 -> 7.464996 | D37: =D32*1000/D40 -> 9.0668379 | E37: =E32*1000/E40 -> 9.9597845 | F37: =F32*1000/F40 -> 11.001451
A39: Weighted-avg shares — Basic | B39: =AVERAGE('Quarterly Income Statement'!B40,'Quarterly Income Statement'!C40,'Quarterly Income Statement'!D40,'Quarterly Income Statement'!E40) -> 15343782 | C39: =AVERAGE('Quarterly Income Statement'!F40,'Quarterly Income Statement'!G40,'Quarterly Income Statement'!H40,'Quarterly Income Statement'!I40) -> 14948500 | D39: =AVERAGE('Quarterly Income Statement'!J40,'Quarterly Income Statement'!K40,'Quarterly Income Statement'!L40,'Quarterly Income Statement'!M40) -> 14653077 | E39: =AVERAGE('Quarterly Income Statement'!N40,'Quarterly Income Statement'!O40,'Quarterly Income Statement'!P40,'Quarterly Income Statement'!Q40) -> 14422851 | F39: =AVERAGE('Quarterly Income Statement'!R40,'Quarterly Income Statement'!S40,'Quarterly Income Statement'!T40,'Quarterly Income Statement'!U40) -> 14242541
A40: Weighted-avg shares — Diluted | B40: =AVERAGE('Quarterly Income Statement'!B41,'Quarterly Income Statement'!C41,'Quarterly Income Statement'!D41,'Quarterly Income Statement'!E41) -> 15408094 | C40: =AVERAGE('Quarterly Income Statement'!F41,'Quarterly Income Statement'!G41,'Quarterly Income Statement'!H41,'Quarterly Income Statement'!I41) -> 15004696 | D40: =AVERAGE('Quarterly Income Statement'!J41,'Quarterly Income Statement'!K41,'Quarterly Income Statement'!L41,'Quarterly Income Statement'!M41) -> 14711742 | E40: =AVERAGE('Quarterly Income Statement'!N41,'Quarterly Income Statement'!O41,'Quarterly Income Statement'!P41,'Quarterly Income Statement'!Q41) -> 14483682 | F40: =AVERAGE('Quarterly Income Statement'!R41,'Quarterly Income Statement'!S41,'Quarterly Income Statement'!T41,'Quarterly Income Statement'!U41) -> 14302612
