Workbook

Sheet Notes
B1: Apple Inc. (AAPL) — Quarterly Income Statement Forecast, FY2026Q4–FY2028
B2: Actuals FY2024–FY2026 Q3, forecast FY2026 Q4 through FY2028 Q4. $ in millions except per-share amounts.
B4: Data sources (actuals)
B5: • FY2024 & FY2025 (full years, all quarters) and FY2026 Q1–Q3: Apple Inc. Condensed Consolidated Statements of Operations, as filed with the SEC (Form 8-K Exhibit 99.1 quarterly press releases and Form 10-K), sourced from SEC EDGAR (sec.gov/cgi-bin/browse-edgar?action=getcompany&CIK=0000320193) and apple.com/newsroom. All figures are GAAP as reported.
B6: • Products/Services split of gross margin is not printed by Apple as a separate line; Products and Services gross margin $ are computed here as (segment net sales − segment cost of sales), which is an exact, unambiguous derivation from Apple's reported figures.
B7: • FY2026 Q4 (forecast) is grounded in Apple's official guidance given on the fiscal Q3 2026 earnings call (July 30, 2026): total revenue growth of 9%–11% YoY (2.5pp FX headwind, supply constraints on iPhone/Mac/iPad cited), gross margin of 47%–48% (including ~1pp tariff-refund benefit, down from Q3's ~2pp benefit), and operating expenses of $19.1B–$19.4B. The assumptions below were calibrated to land near the midpoint of each guided range.
B9: FY2027–FY2028 forecast methodology
B10: • Built bottom-up on the Assumptions sheet: Products and Services net sales are grown at assumed year-over-year rates off the same fiscal quarter one year prior (preserving Apple's strong seasonality, e.g. fiscal Q1 = holiday quarter). Products revenue growth is assumed to moderate from FY2026's iPhone 17-driven mid-to-high-teens pace to a normalized mid-single-digit rate; Services growth is assumed to remain low-double-digit, consistent with its multi-year trend, decelerating only gradually.
B11: • Gross margin: Products margin assumed to settle around 36.5%–37.3% (in line with the FY2025 run-rate of ~36%, after FY2026's temporary tariff-refund boost fades, with slow mix/efficiency-driven expansion). Services margin assumed to keep expanding gradually from ~75.5% toward ~76.8%, continuing its multi-year trend.
B12: • Operating expenses are modeled as a % of total revenue. R&D intensity is assumed to keep rising (from ~10.5% to ~11.0% of revenue) reflecting Apple's stated step-up in AI/Siri investment; SG&A is held roughly flat at ~6.4%–6.5% of revenue.
B13: • Effective tax rate is assumed to keep drifting up gradually (18.0% → 18.3%), continuing the trend visible through FY2026 (14.7% in FY2025 Q1 up to 17.9% in FY2026 Q3), driven by new U.S. Treasury foreign-currency-loss regulations effective December 2024 and other international tax changes.
B14: • Diluted share count is assumed to keep declining ~0.5% per quarter (~2% per year) from continued share buybacks — consistent with Apple's realized pace of roughly $90–100B in annual repurchases and its newest $100B buyback authorization (approved April 30, 2026).
... B25: • Workbook built August 17, 2026.

Sheet Assumptions
A1: Forecast Assumptions — FY2026 Q4 through FY2028 Q4
A2: Editable drivers. All forecast formulas in the Income Statement sheet reference these cells.
A4: Fiscal Quarter | B4: Q4 FY26 | C4: Q1 FY27 | D4: Q2 FY27 | E4: Q3 FY27 | F4: Q4 FY27 | G4: Q1 FY28 | H4: Q2 FY28 | I4: Q3 FY28 | J4: Q4 FY28
B5: ~Sep 26, 2026 (est.) | C5: ~Dec 26, 2026 (est.) | D5: ~Mar 27, 2027 (est.) | E5: ~Jun 26, 2027 (est.) | F5: ~Sep 25, 2027 (est.) | G5: ~Dec 25, 2027 (est.) | H5: ~Mar 25, 2028 (est.) | I5: ~Jun 24, 2028 (est.) | J5: ~Sep 30, 2028 (est.)
A6: Revenue Growth (Year-over-Year %)
A7: Products net sales — YoY growth % | B7: 0.095 | C7: 0.06 | D7: 0.055 | E7: 0.05 | F7: 0.05 | G7: 0.055 | H7: 0.05 | I7: 0.05 | J7: 0.05
A8: Services net sales — YoY growth % | B8: 0.11 | C8: 0.11 | D8: 0.105 | E8: 0.105 | F8: 0.105 | G8: 0.1 | H8: 0.1 | I8: 0.1 | J8: 0.1
A10: Gross Margin Assumptions
A11: Products gross margin % | B11: 0.364 | C11: 0.385 | D11: 0.36 | E11: 0.355 | F11: 0.365 | G11: 0.387 | H11: 0.362 | I11: 0.357 | J11: 0.367
A12: Services gross margin % | B12: 0.755 | C12: 0.76 | D12: 0.76 | E12: 0.762 | F12: 0.763 | G12: 0.765 | H12: 0.765 | I12: 0.767 | J12: 0.768
A14: Operating Expense Assumptions (Year-over-Year $ growth, off same prior-year quarter)
A15: Research & development — YoY $ growth % | B15: 0.32 | C15: 0.2 | D15: 0.15 | E15: 0.12 | F15: 0.12 | G15: 0.1 | H15: 0.09 | I15: 0.08 | J15: 0.08
A16: Selling, general & administrative — YoY $ growth % | B16: 0.07 | C16: 0.08 | D16: 0.08 | E16: 0.07 | F16: 0.07 | G16: 0.07 | H16: 0.07 | I16: 0.06 | J16: 0.06
A18: Other Assumptions
A19: Other income/(expense), net ($M) | B19: 150 | C19: 150 | D19: 150 | E19: 150 | F19: 150 | G19: 150 | H19: 150 | I19: 150 | J19: 150
A20: Effective tax rate % | B20: 0.18 | C20: 0.18 | D20: 0.18 | E20: 0.182 | F20: 0.182 | G20: 0.182 | H20: 0.183 | I20: 0.183 | J20: 0.183
A21: Diluted shares — sequential (QoQ) change % (buybacks) | B21: -0.005 | C21: -0.005 | D21: -0.005 | E21: -0.005 | F21: -0.005 | G21: -0.005 | H21: -0.005 | I21: -0.005 | J21: -0.005
A22: Basic/diluted share dilution spread (M shares) | B22: 55 | C22: 55 | D22: 55 | E22: 55 | F22: 55 | G22: 55 | H22: 55 | I22: 55 | J22: 55

Sheet Income Statement
A1: Apple Inc. (AAPL) — Quarterly Income Statement: Actuals & Forecast
A2: $ in millions, except per-share amounts; share counts in millions. Actual quarters shaded blue, forecast quarters shaded amber.
B4: Q1 FY24 | C4: Q2 FY24 | D4: Q3 FY24 | E4: Q4 FY24 | F4: FY24 Total | G4: Q1 FY25 | H4: Q2 FY25 | I4: Q3 FY25 | J4: Q4 FY25 | K4: FY25 Total | L4: Q1 FY26 | M4: Q2 FY26 | N4: Q3 FY26 | O4: Q4 FY26 | P4: FY26 Total | Q4: Q1 FY27 | R4: Q2 FY27 | S4: Q3 FY27 | T4: Q4 FY27 | U4: FY27 Total | V4: Q1 FY28 | W4: Q2 FY28 | X4: Q3 FY28 | Y4: Q4 FY28 | Z4: FY28 Total
B5: Dec 30, 2023 | C5: Mar 30, 2024 | D5: Jun 29, 2024 | E5: Sep 28, 2024 | F5: Fiscal Year | G5: Dec 28, 2024 | H5: Mar 29, 2025 | I5: Jun 28, 2025 | J5: Sep 27, 2025 | K5: Fiscal Year | L5: Dec 27, 2025 | M5: Mar 28, 2026 | N5: Jun 27, 2026 | O5: ~Sep 26, 2026 (est.) | P5: Fiscal Year | Q5: ~Dec 26, 2026 (est.) | R5: ~Mar 27, 2027 (est.) | S5: ~Jun 26, 2027 (est.) | T5: ~Sep 25, 2027 (est.) | U5: Fiscal Year | V5: ~Dec 25, 2027 (est.) | W5: ~Mar 25, 2028 (est.) | X5: ~Jun 24, 2028 (est.) | Y5: ~Sep 30, 2028 (est.) | Z5: Fiscal Year
B6: Actual | C6: Actual | D6: Actual | E6: Actual | F6: Actual | G6: Actual | H6: Actual | I6: Actual | J6: Actual | K6: Actual | L6: Actual | M6: Actual | N6: Actual | O6: Forecast | P6: Actual + Forecast | Q6: Forecast | R6: Forecast | S6: Forecast | T6: Forecast | U6: Forecast | V6: Forecast | W6: Forecast | X6: Forecast | Y6: Forecast | Z6: Forecast
A8: Net Sales
A9: Products | B9: 96458 | C9: 66886 | D9: 61564 | E9: 69958 | F9: =SUM(B9:E9) -> 294866 | G9: 97960 | H9: 68714 | I9: 66613 | J9: 73716 | K9: =SUM(G9:J9) -> 307003 | L9: 113743 | M9: 80208 | N9: 78678 | O9: =J9*(1+Assumptions!B7) -> 80719.02 | P9: =SUM(L9:O9) -> 353348.02 | Q9: =L9*(1+Assumptions!C7) -> 120567.58 | R9: =M9*(1+Assumptions!D7) -> 84619.44 | S9: =N9*(1+Assumptions!E7) -> 82611.9 | T9: =O9*(1+Assumptions!F7) -> 84754.971 | U9: =SUM(Q9:T9) -> 372553.89 | V9: =Q9*(1+Assumptions!G7) -> 127198.8 | W9: =R9*(1+Assumptions!H7) -> 88850.412 | X9: =S9*(1+Assumptions!I7) -> 86742.495 | Y9: =T9*(1+Assumptions!J7) -> 88992.72 | Z9: =SUM(V9:Y9) -> 391784.42
A10: Services | B10: 23117 | C10: 23867 | D10: 24213 | E10: 24972 | F10: =SUM(B10:E10) -> 96169 | G10: 26340 | H10: 26645 | I10: 27423 | J10: 28750 | K10: =SUM(G10:J10) -> 109158 | L10: 30013 | M10: 30976 | N10: 30739 | O10: =J10*(1+Assumptions!B8) -> 31912.5 | P10: =SUM(L10:O10) -> 123640.5 | Q10: =L10*(1+Assumptions!C8) -> 33314.43 | R10: =M10*(1+Assumptions!D8) -> 34228.48 | S10: =N10*(1+Assumptions!E8) -> 33966.595 | T10: =O10*(1+Assumptions!F8) -> 35263.312 | U10: =SUM(Q10:T10) -> 136772.82 | V10: =Q10*(1+Assumptions!G8) -> 36645.873 | W10: =R10*(1+Assumptions!H8) -> 37651.328 | X10: =S10*(1+Assumptions!I8) -> 37363.255 | Y10: =T10*(1+Assumptions!J8) -> 38789.644 | Z10: =SUM(V10:Y10) -> 150450.1
A11: Total net sales | B11: =B9+B10 -> 119575 | C11: =C9+C10 -> 90753 | D11: =D9+D10 -> 85777 | E11: =E9+E10 -> 94930 | F11: =F9+F10 -> 391035 | G11: =G9+G10 -> 124300 | H11: =H9+H10 -> 95359 | I11: =I9+I10 -> 94036 | ... Z11: =Z9+Z10 -> 542234.52
A12: YoY growth % | G12: =G11/B11-1 -> 0.039514949 | H12: =H11/C11-1 -> 0.050753143 | I12: =I11/D11-1 -> 0.096284552 | J12: =J11/E11-1 -> 0.07938481 | K12: =K11/F11-1 -> 0.064255118 | L12: =L11/G11-1 -> 0.15652454 | M12: =M11/H11-1 -> 0.16595182 | N12: =N11/I11-1 -> 0.16356502 | ... Z12: =Z11/U11-1 -> 0.064610423
A14: Cost of Sales
A15: Products | B15: 58440 | C15: 42424 | D15: 39803 | E15: 44566 | F15: =SUM(B15:E15) -> 185233 | G15: 59447 | H15: 44030 | I15: 43620 | J15: 47019 | K15: =SUM(G15:J15) -> 194116 | L15: 67478 | M15: 49179 | N15: 47153 | O15: =O9*(1-Assumptions!B11) -> 51337.297 | P15: =SUM(L15:O15) -> 215147.3 | Q15: =Q9*(1-Assumptions!C11) -> 74149.062 | R15: =R9*(1-Assumptions!D11) -> 54156.442 | S15: =S9*(1-Assumptions!E11) -> 53284.675 | T15: =T9*(1-Assumptions!F11) -> 53819.407 | U15: =SUM(Q15:T15) -> 235409.59 | V15: =V9*(1-Assumptions!G11) -> 77972.862 | W15: =W9*(1-Assumptions!H11) -> 56686.563 | X15: =X9*(1-Assumptions!I11) -> 55775.424 | Y15: =Y9*(1-Assumptions!J11) -> 56332.391 | Z15: =SUM(V15:Y15) -> 246767.24
A16: Services | B16: 6280 | C16: 6058 | D16: 6296 | E16: 6485 | F16: =SUM(B16:E16) -> 25119 | G16: 6578 | H16: 6462 | I16: 6698 | J16: 7106 | K16: =SUM(G16:J16) -> 26844 | L16: 7047 | M16: 7224 | N16: 7494 | O16: =O10*(1-Assumptions!B12) -> 7818.5625 | P16: =SUM(L16:O16) -> 29583.562 | Q16: =Q10*(1-Assumptions!C12) -> 7995.4632 | R16: =R10*(1-Assumptions!D12) -> 8214.8352 | S16: =S10*(1-Assumptions!E12) -> 8084.0496 | T16: =T10*(1-Assumptions!F12) -> 8357.4051 | U16: =SUM(Q16:T16) -> 32651.753 | V16: =V10*(1-Assumptions!G12) -> 8611.7802 | W16: =W10*(1-Assumptions!H12) -> 8848.0621 | X16: =X10*(1-Assumptions!I12) -> 8705.6383 | Y16: =Y10*(1-Assumptions!J12) -> 8999.1974 | Z16: =SUM(V16:Y16) -> 35164.678
A17: Total cost of sales | B17: =B15+B16 -> 64720 | C17: =C15+C16 -> 48482 | D17: =D15+D16 -> 46099 | E17: =E15+E16 -> 51051 | F17: =F15+F16 -> 210352 | G17: =G15+G16 -> 66025 | H17: =H15+H16 -> 50492 | I17: =I15+I16 -> 50318 | ... Z17: =Z15+Z16 -> 281931.92
A19: Gross Margin
A20: Products gross margin | B20: =B9-B15 -> 38018 | C20: =C9-C15 -> 24462 | D20: =D9-D15 -> 21761 | E20: =E9-E15 -> 25392 | F20: =F9-F15 -> 109633 | G20: =G9-G15 -> 38513 | H20: =H9-H15 -> 24684 | I20: =I9-I15 -> 22993 | ... Z20: =Z9-Z15 -> 145017.18
A21: Services gross margin | B21: =B10-B16 -> 16837 | C21: =C10-C16 -> 17809 | D21: =D10-D16 -> 17917 | E21: =E10-E16 -> 18487 | F21: =F10-F16 -> 71050 | G21: =G10-G16 -> 19762 | H21: =H10-H16 -> 20183 | I21: =I10-I16 -> 20725 | ... Z21: =Z10-Z16 -> 115285.42
A22: Total gross margin | B22: =B20+B21 -> 54855 | C22: =C20+C21 -> 42271 | D22: =D20+D21 -> 39678 | E22: =E20+E21 -> 43879 | F22: =F20+F21 -> 180683 | G22: =G20+G21 -> 58275 | H22: =H20+H21 -> 44867 | I22: =I20+I21 -> 43718 | ... Z22: =Z20+Z21 -> 260302.6
A23: Gross margin % | B23: =B22/B11 -> 0.45874974 | C23: =C22/C11 -> 0.46578075 | D23: =D22/D11 -> 0.46257155 | E23: =E22/E11 -> 0.4622248 | F23: =F22/F11 -> 0.4620635 | G23: =G22/G11 -> 0.46882542 | H23: =H22/H11 -> 0.47050619 | I23: =I22/I11 -> 0.46490706 | ... Z23: =Z22/Z11 -> 0.48005539
A25: Operating Expenses
A26: Research & development | B26: 7696 | C26: 7903 | D26: 8006 | E26: 7765 | F26: =SUM(B26:E26) -> 31370 | G26: 8268 | H26: 8550 | I26: 8866 | J26: 8866 | K26: =SUM(G26:J26) -> 34550 | L26: 10887 | M26: 11419 | N26: 11729 | O26: =J26*(1+Assumptions!B15) -> 11703.12 | P26: =SUM(L26:O26) -> 45738.12 | Q26: =L26*(1+Assumptions!C15) -> 13064.4 | R26: =M26*(1+Assumptions!D15) -> 13131.85 | S26: =N26*(1+Assumptions!E15) -> 13136.48 | T26: =O26*(1+Assumptions!F15) -> 13107.494 | U26: =SUM(Q26:T26) -> 52440.224 | V26: =Q26*(1+Assumptions!G15) -> 14370.84 | W26: =R26*(1+Assumptions!H15) -> 14313.717 | X26: =S26*(1+Assumptions!I15) -> 14187.398 | Y26: =T26*(1+Assumptions!J15) -> 14156.094 | Z26: =SUM(V26:Y26) -> 57028.049
A27: Selling, general & administrative | B27: 6786 | C27: 6468 | D27: 6320 | E27: 6523 | F27: =SUM(B27:E27) -> 26097 | G27: 7175 | H27: 6728 | I27: 6650 | J27: 7048 | K27: =SUM(G27:J27) -> 27601 | L27: 7492 | M27: 7477 | N27: 7346 | O27: =J27*(1+Assumptions!B16) -> 7541.36 | P27: =SUM(L27:O27) -> 29856.36 | Q27: =L27*(1+Assumptions!C16) -> 8091.36 | R27: =M27*(1+Assumptions!D16) -> 8075.16 | S27: =N27*(1+Assumptions!E16) -> 7860.22 | T27: =O27*(1+Assumptions!F16) -> 8069.2552 | U27: =SUM(Q27:T27) -> 32095.995 | V27: =Q27*(1+Assumptions!G16) -> 8657.7552 | W27: =R27*(1+Assumptions!H16) -> 8640.4212 | X27: =S27*(1+Assumptions!I16) -> 8331.8332 | Y27: =T27*(1+Assumptions!J16) -> 8553.4105 | Z27: =SUM(V27:Y27) -> 34183.42
A28: Total operating expenses | B28: =B26+B27 -> 14482 | C28: =C26+C27 -> 14371 | D28: =D26+D27 -> 14326 | E28: =E26+E27 -> 14288 | F28: =F26+F27 -> 57467 | G28: =G26+G27 -> 15443 | H28: =H26+H27 -> 15278 | I28: =I26+I27 -> 15516 | ... Z28: =Z26+Z27 -> 91211.469
A30: Operating income | B30: =B22-B28 -> 40373 | C30: =C22-C28 -> 27900 | D30: =D22-D28 -> 25352 | E30: =E22-E28 -> 29591 | F30: =F22-F28 -> 123216 | G30: =G22-G28 -> 42832 | H30: =H22-H28 -> 29589 | I30: =I22-I28 -> 28202 | ... Z30: =Z22-Z28 -> 169091.13
A31: Operating margin % | B31: =B30/B11 -> 0.33763747 | C31: =C30/C11 -> 0.30742785 | D31: =D30/D11 -> 0.29555708 | E31: =E30/E11 -> 0.31171389 | F31: =F30/F11 -> 0.31510223 | G31: =G30/G11 -> 0.34458568 | H31: =H30/H11 -> 0.31029059 | I31: =I30/I11 -> 0.29990642 | ... Z31: =Z30/Z11 -> 0.31184133
A33: Other income/(expense), net | B33: -50 | C33: 158 | D33: 142 | E33: 19 | F33: =SUM(B33:E33) -> 269 | G33: -248 | H33: -279 | I33: -171 | J33: 377 | K33: =SUM(G33:J33) -> -321 | L33: 150 | M33: -52 | N33: 572 | O33: =Assumptions!B19 -> 150 | P33: =SUM(L33:O33) -> 820 | Q33: =Assumptions!C19 -> 150 | R33: =Assumptions!D19 -> 150 | S33: =Assumptions!E19 -> 150 | T33: =Assumptions!F19 -> 150 | U33: =SUM(Q33:T33) -> 600 | V33: =Assumptions!G19 -> 150 | W33: =Assumptions!H19 -> 150 | X33: =Assumptions!I19 -> 150 | Y33: =Assumptions!J19 -> 150 | Z33: =SUM(V33:Y33) -> 600
A34: Income before provision for income taxes | B34: =B30+B33 -> 40323 | C34: =C30+C33 -> 28058 | D34: =D30+D33 -> 25494 | E34: =E30+E33 -> 29610 | F34: =F30+F33 -> 123485 | G34: =G30+G33 -> 42584 | H34: =H30+H33 -> 29310 | I34: =I30+I33 -> 28031 | ... Z34: =Z30+Z33 -> 169691.13
A35: Provision for income taxes | B35: 6407 | C35: 4422 | D35: 4046 | E35: 14874 | F35: =SUM(B35:E35) -> 29749 | G35: 6254 | H35: 4530 | I35: 4597 | J35: 5338 | K35: =SUM(G35:J35) -> 20719 | L35: 8905 | M35: 6255 | N35: 6478 | O35: =O34*Assumptions!B20 -> 6188.6125 | P35: =SUM(L35:O35) -> 27826.613 | Q35: =Q34*Assumptions!C20 -> 9131.7105 | R35: =R34*Assumptions!D20 -> 6375.534 | S35: =S34*Assumptions!E20 -> 6254.0787 | T35: =T34*Assumptions!F20 -> 6700.2794 | U35: =SUM(Q35:T35) -> 28461.603 | V35: =V34*Assumptions!G20 -> 9897.4206 | W35: =W34*Assumptions!H20 -> 6983.8249 | X35: =X34*Assumptions!I20 -> 6817.7483 | Y35: =Y34*Assumptions!J20 -> 7300.1024 | Z35: =SUM(V35:Y35) -> 30999.096
A36: Effective tax rate % | B36: =B35/B34 -> 0.15889195 | C36: =C35/C34 -> 0.15760211 | D36: =D35/D34 -> 0.15870401 | E36: =E35/E34 -> 0.50233029 | F36: =F35/F34 -> 0.24091185 | G36: =G35/G34 -> 0.14686267 | H36: =H35/H34 -> 0.15455476 | I36: =I35/I34 -> 0.163997 | ... Z36: =Z35/Z34 -> 0.18267953
A37: Net income | B37: =B34-B35 -> 33916 | C37: =C34-C35 -> 23636 | D37: =D34-D35 -> 21448 | E37: =E34-E35 -> 14736 | F37: =F34-F35 -> 93736 | G37: =G34-G35 -> 36330 | H37: =H34-H35 -> 24780 | I37: =I34-I35 -> 23434 | ... Z37: =Z34-Z35 -> 138692.04
A38: Net margin % | B38: =B37/B11 -> 0.28363788 | C38: =C37/C11 -> 0.26044318 | D38: =D37/D11 -> 0.25004372 | E38: =E37/E11 -> 0.15523017 | F38: =F37/F11 -> 0.23971256 | G38: =G37/G11 -> 0.29227675 | H38: =H37/H11 -> 0.25986011 | I38: =I37/I11 -> 0.24920243 | ... Z38: =Z37/Z11 -> 0.25577869
A40: Per Share Data
A41: Basic earnings per share | B41: =B37/B44 -> 2.1867517 | C41: =C37/C44 -> 1.5342218 | D41: =D37/D44 -> 1.4029744 | E41: =E37/E44 -> 0.97126349 | F41: =F37/F44 -> 6.1090543 | G41: =G37/G44 -> 2.4088758 | H41: =H37/H44 -> 1.652652 | I41: =I37/I44 -> 1.5724471 | ... Z41: =Z37/Z44 -> 9.8244814
A42: Diluted earnings per share | B42: =B37/B45 -> 2.1773629 | C42: =C37/C45 -> 1.5283831 | D42: =D37/D45 -> 1.39743 | E42: =E37/E45 -> 0.96674815 | F42: =F37/F45 -> 6.0835556 | G42: =G37/G45 -> 2.3978829 | H42: =H37/H45 -> 1.6458409 | I42: =I37/I45 -> 1.5676826 | ... Z42: =Z37/Z45 -> 9.7863536
A44: Basic weighted-avg shares outstanding | B44: 15509.763 | C44: 15405.856 | D44: 15287.521 | E44: 15171.99 | F44: =AVERAGE(B44:E44) -> 15343.782 | G44: 15081.724 | H44: 14994.082 | I44: 14902.886 | J44: 14815.307 | K44: =AVERAGE(G44:J44) -> 14948.5 | L44: 14748.158 | M44: 14673.278 | N44: 14656.11 | O44: =O45-Assumptions!B22 -> 14586.103 | P44: =AVERAGE(L44:O44) -> 14665.912 | Q44: =Q45-Assumptions!C22 -> 14512.897 | R44: =R45-Assumptions!D22 -> 14440.058 | S44: =S45-Assumptions!E22 -> 14367.582 | T44: =T45-Assumptions!F22 -> 14295.469 | U44: =AVERAGE(Q44:T44) -> 14404.002 | V44: =V45-Assumptions!G22 -> 14223.717 | W44: =W45-Assumptions!H22 -> 14152.323 | X44: =X45-Assumptions!I22 -> 14081.287 | Y44: =Y45-Assumptions!J22 -> 14010.605 | Z44: =AVERAGE(V44:Y44) -> 14116.983
A45: Diluted weighted-avg shares outstanding | B45: 15576.641 | C45: 15464.709 | D45: 15348.175 | E45: 15242.853 | F45: =AVERAGE(B45:E45) -> 15408.094 | G45: 15150.865 | H45: 15056.133 | I45: 14948.179 | J45: 14863.609 | K45: =AVERAGE(G45:J45) -> 15004.697 | L45: 14810.356 | M45: 14725.873 | N45: 14714.676 | O45: =N45*(1+Assumptions!B21) -> 14641.103 | P45: =AVERAGE(L45:O45) -> 14723.002 | Q45: =O45*(1+Assumptions!C21) -> 14567.897 | R45: =Q45*(1+Assumptions!D21) -> 14495.058 | S45: =R45*(1+Assumptions!E21) -> 14422.582 | T45: =S45*(1+Assumptions!F21) -> 14350.469 | U45: =AVERAGE(Q45:T45) -> 14459.002 | V45: =T45*(1+Assumptions!G21) -> 14278.717 | W45: =V45*(1+Assumptions!H21) -> 14207.323 | X45: =W45*(1+Assumptions!I21) -> 14136.287 | Y45: =X45*(1+Assumptions!J21) -> 14065.605 | Z45: =AVERAGE(V45:Y45) -> 14171.983
