Workbook

Sheet Assumptions
A1: Apple Inc. (AAPL) — Forecast Assumptions
A2: Drives Income Statement forecast columns Q4 FY2026E through Q4 FY2028E. Revenue growth rates are year-over-year vs. the same fiscal quarter one year prior.
A3: Historical actuals (FY2024A, FY2025A, and Q1-Q3 FY2026A) are hardcoded on the Income Statement tab from Apple's SEC filings/press releases and are NOT driven by these assumptions.
A5: Assumption | B5: Q4 FY26E | C5: Q1 FY27E | D5: Q2 FY27E | E5: Q3 FY27E | F5: Q4 FY27E | G5: Q1 FY28E | H5: Q2 FY28E | I5: Q3 FY28E | J5: Q4 FY28E
A7: Revenue Growth — Year-over-Year (%)
A8: iPhone | B8: 0.13 | C8: 0.08 | D8: 0.08 | E8: 0.08 | F8: 0.08 | G8: 0.06 | H8: 0.06 | I8: 0.06 | J8: 0.06
A9: Mac | B9: 0.04 | C9: 0.05 | D9: 0.05 | E9: 0.05 | F9: 0.05 | G9: 0.05 | H9: 0.05 | I9: 0.05 | J9: 0.05
A10: iPad | B10: 0.02 | C10: 0.04 | D10: 0.04 | E10: 0.04 | F10: 0.04 | G10: 0.04 | H10: 0.04 | I10: 0.04 | J10: 0.04
A11: Wearables, Home and Accessories | B11: 0.01 | C11: 0.03 | D11: 0.03 | E11: 0.03 | F11: 0.03 | G11: 0.03 | H11: 0.03 | I11: 0.03 | J11: 0.03
A12: Services | B12: 0.12 | C12: 0.12 | D12: 0.12 | E12: 0.12 | F12: 0.12 | G12: 0.11 | H12: 0.11 | I12: 0.11 | J12: 0.11
A14: Gross Margin Assumptions (%)
A15: Products Gross Margin % | B15: 0.365 | C15: 0.38 | D15: 0.38 | E15: 0.38 | F15: 0.38 | G15: 0.385 | H15: 0.385 | I15: 0.385 | J15: 0.385
A16: Services Gross Margin % | B16: 0.755 | C16: 0.76 | D16: 0.76 | E16: 0.76 | F16: 0.76 | G16: 0.765 | H16: 0.765 | I16: 0.765 | J16: 0.765
A18: Operating Expenses — Year-over-Year Growth (%)
A19: Research & Development — YoY growth % | B19: 0.3 | C19: 0.14 | D19: 0.14 | E19: 0.14 | F19: 0.14 | G19: 0.09 | H19: 0.09 | I19: 0.09 | J19: 0.09
A20: Selling, General & Administrative — YoY growth % | B20: 0.09 | C20: 0.075 | D20: 0.075 | E20: 0.075 | F20: 0.075 | G20: 0.065 | H20: 0.065 | I20: 0.065 | J20: 0.065
A22: Other Assumptions
A23: Other Income/(Expense), net ($M per quarter) | B23: 200 | C23: 200 | D23: 200 | E23: 200 | F23: 200 | G23: 225 | H23: 225 | I23: 225 | J23: 225
A24: Effective Tax Rate % | B24: 0.175 | C24: 0.175 | D24: 0.175 | E24: 0.175 | F24: 0.175 | G24: 0.175 | H24: 0.175 | I24: 0.175 | J24: 0.175
A25: Diluted Shares — Sequential QoQ Change % | B25: -0.0035 | C25: -0.0035 | D25: -0.0035 | E25: -0.0035 | F25: -0.0035 | G25: -0.0035 | H25: -0.0035 | I25: -0.0035 | J25: -0.0035
A26: Basic / Diluted Share Ratio | B26: 0.996 | C26: 0.996 | D26: 0.996 | E26: 0.996 | F26: 0.996 | G26: 0.996 | H26: 0.996 | I26: 0.996 | J26: 0.996

Sheet Income Statement
A1: Apple Inc. (AAPL) — Income Statement: Actual Results & Forecast (FY2026E–FY2028E)
A2: $ in millions, except per-share amounts and shares (in thousands). Apple's fiscal year ends the last Saturday of September.
A3: Blue = hardcoded actual (SEC filings / Apple press releases). Black = same-sheet formula. Green = formula linked to the Assumptions tab.
B5: FY2024 | C5: FY2025 | H5: FY2026 | M5: FY2027 | R5: FY2028
B6: FY2024A | C6: Q1 FY25A | D6: Q2 FY25A | E6: Q3 FY25A | F6: Q4 FY25A | G6: FY2025A | H6: Q1 FY26A | I6: Q2 FY26A | J6: Q3 FY26A | K6: Q4 FY26E | L6: FY2026E | M6: Q1 FY27E | N6: Q2 FY27E | O6: Q3 FY27E | P6: Q4 FY27E | Q6: FY2027E | R6: Q1 FY28E | S6: Q2 FY28E | T6: Q3 FY28E | U6: Q4 FY28E | V6: FY2028E
A8: Net Sales by Category
A9: iPhone | B9: 201183 | C9: 69138 | D9: 46841 | E9: 44582 | F9: 49025 | G9: =SUM(C9:F9) -> 209586 | H9: 85269 | I9: 56994 | J9: 54252 | K9: =F9*(1+Assumptions!B8) -> 55398.25 | L9: =SUM(H9:K9) -> 251913.25 | M9: =H9*(1+Assumptions!C8) -> 92090.52 | N9: =I9*(1+Assumptions!D8) -> 61553.52 | O9: =J9*(1+Assumptions!E8) -> 58592.16 | P9: =K9*(1+Assumptions!F8) -> 59830.11 | Q9: =SUM(M9:P9) -> 272066.31 | R9: =M9*(1+Assumptions!G8) -> 97615.951 | S9: =N9*(1+Assumptions!H8) -> 65246.731 | T9: =O9*(1+Assumptions!I8) -> 62107.69 | U9: =P9*(1+Assumptions!J8) -> 63419.917 | V9: =SUM(R9:U9) -> 288390.29
A10: Mac | B10: 29984 | C10: 8987 | D10: 7949 | E10: 8046 | F10: 8726 | G10: =SUM(C10:F10) -> 33708 | H10: 8386 | I10: 8399 | J10: 10352 | K10: =F10*(1+Assumptions!B9) -> 9075.04 | L10: =SUM(H10:K10) -> 36212.04 | M10: =H10*(1+Assumptions!C9) -> 8805.3 | N10: =I10*(1+Assumptions!D9) -> 8818.95 | O10: =J10*(1+Assumptions!E9) -> 10869.6 | P10: =K10*(1+Assumptions!F9) -> 9528.792 | Q10: =SUM(M10:P10) -> 38022.642 | R10: =M10*(1+Assumptions!G9) -> 9245.565 | S10: =N10*(1+Assumptions!H9) -> 9259.8975 | T10: =O10*(1+Assumptions!I9) -> 11413.08 | U10: =P10*(1+Assumptions!J9) -> 10005.232 | V10: =SUM(R10:U10) -> 39923.774
A11: iPad | B11: 26694 | C11: 8088 | D11: 6402 | E11: 6581 | F11: 6952 | G11: =SUM(C11:F11) -> 28023 | H11: 8595 | I11: 6914 | J11: 6191 | K11: =F11*(1+Assumptions!B10) -> 7091.04 | L11: =SUM(H11:K11) -> 28791.04 | M11: =H11*(1+Assumptions!C10) -> 8938.8 | N11: =I11*(1+Assumptions!D10) -> 7190.56 | O11: =J11*(1+Assumptions!E10) -> 6438.64 | P11: =K11*(1+Assumptions!F10) -> 7374.6816 | Q11: =SUM(M11:P11) -> 29942.682 | R11: =M11*(1+Assumptions!G10) -> 9296.352 | S11: =N11*(1+Assumptions!H10) -> 7478.1824 | T11: =O11*(1+Assumptions!I10) -> 6696.1856 | U11: =P11*(1+Assumptions!J10) -> 7669.6689 | V11: =SUM(R11:U11) -> 31140.389
A12: Wearables, Home and Accessories | B12: 37005 | C12: 11747 | D12: 7522 | E12: 7404 | F12: 9013 | G12: =SUM(C12:F12) -> 35686 | H12: 11493 | I12: 7901 | J12: 7883 | K12: =F12*(1+Assumptions!B11) -> 9103.13 | L12: =SUM(H12:K12) -> 36380.13 | M12: =H12*(1+Assumptions!C11) -> 11837.79 | N12: =I12*(1+Assumptions!D11) -> 8138.03 | O12: =J12*(1+Assumptions!E11) -> 8119.49 | P12: =K12*(1+Assumptions!F11) -> 9376.2239 | Q12: =SUM(M12:P12) -> 37471.534 | R12: =M12*(1+Assumptions!G11) -> 12192.924 | S12: =N12*(1+Assumptions!H11) -> 8382.1709 | T12: =O12*(1+Assumptions!I11) -> 8363.0747 | U12: =P12*(1+Assumptions!J11) -> 9657.5106 | V12: =SUM(R12:U12) -> 38595.68
A13: Total Products | B13: =B9+B10+B11+B12 -> 294866 | C13: =C9+C10+C11+C12 -> 97960 | D13: =D9+D10+D11+D12 -> 68714 | E13: =E9+E10+E11+E12 -> 66613 | F13: =F9+F10+F11+F12 -> 73716 | G13: =G9+G10+G11+G12 -> 307003 | H13: =H9+H10+H11+H12 -> 113743 | I13: =I9+I10+I11+I12 -> 80208 | ... V13: =V9+V10+V11+V12 -> 398050.13
A14: Services | B14: 96169 | C14: 26340 | D14: 26645 | E14: 27423 | F14: 28750 | G14: =SUM(C14:F14) -> 109158 | H14: 30013 | I14: 30976 | J14: 30739 | K14: =F14*(1+Assumptions!B12) -> 32200 | L14: =SUM(H14:K14) -> 123928 | M14: =H14*(1+Assumptions!C12) -> 33614.56 | N14: =I14*(1+Assumptions!D12) -> 34693.12 | O14: =J14*(1+Assumptions!E12) -> 34427.68 | P14: =K14*(1+Assumptions!F12) -> 36064 | Q14: =SUM(M14:P14) -> 138799.36 | R14: =M14*(1+Assumptions!G12) -> 37312.162 | S14: =N14*(1+Assumptions!H12) -> 38509.363 | T14: =O14*(1+Assumptions!I12) -> 38214.725 | U14: =P14*(1+Assumptions!J12) -> 40031.04 | V14: =SUM(R14:U14) -> 154067.29
A15: Total Net Sales | B15: =B13+B14 -> 391035 | C15: =C13+C14 -> 124300 | D15: =D13+D14 -> 95359 | E15: =E13+E14 -> 94036 | F15: =F13+F14 -> 102466 | G15: =G13+G14 -> 416161 | H15: =H13+H14 -> 143756 | I15: =I13+I14 -> 111184 | ... V15: =V13+V14 -> 552117.42
A16: YoY Growth % | G16: =IFERROR(G15/B15-1,"") -> 0.064255118 | H16: =IFERROR(H15/C15-1,"") -> 0.15652454 | I16: =IFERROR(I15/D15-1,"") -> 0.16595182 | J16: =IFERROR(J15/E15-1,"") -> 0.16356502 | K16: =IFERROR(K15/F15-1,"") -> 0.10151133 | L16: =IFERROR(L15/G15-1,"") -> 0.14673038 | M16: =IFERROR(M15/H15-1,"") -> 0.080212095 | N16: =IFERROR(N15/I15-1,"") -> 0.082837279 | ... V16: =IFERROR(V15/Q15-1,"") -> 0.069368038
A18: Cost of Sales
A19: Products Cost of Sales | B19: 185233 | C19: 59447 | D19: 44030 | E19: 43620 | F19: 47019 | G19: =SUM(C19:F19) -> 194116 | H19: 67478 | I19: 49179 | J19: 47153 | K19: =K13*(1-Assumptions!B15) -> 51223.837 | L19: =SUM(H19:K19) -> 215033.84 | M19: =M13*(1-Assumptions!C15) -> 75436.894 | N19: =N13*(1-Assumptions!D15) -> 53134.657 | O19: =O13*(1-Assumptions!E15) -> 52092.332 | P19: =P13*(1-Assumptions!F15) -> 53388.081 | Q19: =SUM(M19:P19) -> 234051.96 | R19: =R13*(1-Assumptions!G15) -> 78935.737 | S19: =S13*(1-Assumptions!H15) -> 55575.694 | T19: =T13*(1-Assumptions!I15) -> 54476.718 | U19: =U13*(1-Assumptions!J15) -> 55812.682 | V19: =SUM(R19:U19) -> 244800.83
A20: Services Cost of Sales | B20: 25119 | C20: 6578 | D20: 6462 | E20: 6698 | F20: 7106 | G20: =SUM(C20:F20) -> 26844 | H20: 7047 | I20: 7224 | J20: 7494 | K20: =K14*(1-Assumptions!B16) -> 7889 | L20: =SUM(H20:K20) -> 29654 | M20: =M14*(1-Assumptions!C16) -> 8067.4944 | N20: =N14*(1-Assumptions!D16) -> 8326.3488 | O20: =O14*(1-Assumptions!E16) -> 8262.6432 | P20: =P14*(1-Assumptions!F16) -> 8655.36 | Q20: =SUM(M20:P20) -> 33311.846 | R20: =R14*(1-Assumptions!G16) -> 8768.358 | S20: =S14*(1-Assumptions!H16) -> 9049.7004 | T20: =T14*(1-Assumptions!I16) -> 8980.4603 | U20: =U14*(1-Assumptions!J16) -> 9407.2944 | V20: =SUM(R20:U20) -> 36205.813
A21: Total Cost of Sales | B21: =B19+B20 -> 210352 | C21: =C19+C20 -> 66025 | D21: =D19+D20 -> 50492 | E21: =E19+E20 -> 50318 | F21: =F19+F20 -> 54125 | G21: =G19+G20 -> 220960 | H21: =H19+H20 -> 74525 | I21: =I19+I20 -> 56403 | ... V21: =V19+V20 -> 281006.64
A23: Gross Margin ($) | B23: =B15-B21 -> 180683 | C23: =C15-C21 -> 58275 | D23: =D15-D21 -> 44867 | E23: =E15-E21 -> 43718 | F23: =F15-F21 -> 48341 | G23: =G15-G21 -> 195201 | H23: =H15-H21 -> 69231 | I23: =I15-I21 -> 54781 | ... V23: =V15-V21 -> 271110.78
A24: Products Gross Margin % | B24: =IFERROR((B13-B19)/B13,"") -> 0.37180618 | C24: =IFERROR((C13-C19)/C13,"") -> 0.39315027 | D24: =IFERROR((D13-D19)/D13,"") -> 0.3592281 | E24: =IFERROR((E13-E19)/E13,"") -> 0.34517286 | F24: =IFERROR((F13-F19)/F13,"") -> 0.36216018 | G24: =IFERROR((G13-G19)/G13,"") -> 0.3677065 | H24: =IFERROR((H13-H19)/H13,"") -> 0.40675031 | I24: =IFERROR((I13-I19)/I13,"") -> 0.38685667 | ... V24: =IFERROR((V13-V19)/V13,"") -> 0.385
A25: Services Gross Margin % | B25: =IFERROR((B14-B20)/B14,"") -> 0.73880356 | C25: =IFERROR((C14-C20)/C14,"") -> 0.75026576 | D25: =IFERROR((D14-D20)/D14,"") -> 0.75747795 | E25: =IFERROR((E14-E20)/E14,"") -> 0.75575247 | F25: =IFERROR((F14-F20)/F14,"") -> 0.75283478 | G25: =IFERROR((G14-G20)/G14,"") -> 0.75408124 | H25: =IFERROR((H14-H20)/H14,"") -> 0.76520175 | I25: =IFERROR((I14-I20)/I14,"") -> 0.76678719 | ... V25: =IFERROR((V14-V20)/V14,"") -> 0.765
A26: Total Gross Margin % | B26: =IFERROR(B23/B15,"") -> 0.4620635 | C26: =IFERROR(C23/C15,"") -> 0.46882542 | D26: =IFERROR(D23/D15,"") -> 0.47050619 | E26: =IFERROR(E23/E15,"") -> 0.46490706 | F26: =IFERROR(F23/F15,"") -> 0.471776 | G26: =IFERROR(G23/G15,"") -> 0.46905164 | H26: =IFERROR(H23/H15,"") -> 0.48158686 | I26: =IFERROR(I23/I15,"") -> 0.49270579 | ... V26: =IFERROR(V23/V15,"") -> 0.49103826
A28: Operating Expenses
A29: Research & Development | B29: 31370 | C29: 8268 | D29: 8550 | E29: 8866 | F29: 8866 | G29: =SUM(C29:F29) -> 34550 | H29: 10887 | I29: 11419 | J29: 11729 | K29: =F29*(1+Assumptions!B19) -> 11525.8 | L29: =SUM(H29:K29) -> 45560.8 | M29: =H29*(1+Assumptions!C19) -> 12411.18 | N29: =I29*(1+Assumptions!D19) -> 13017.66 | O29: =J29*(1+Assumptions!E19) -> 13371.06 | P29: =K29*(1+Assumptions!F19) -> 13139.412 | Q29: =SUM(M29:P29) -> 51939.312 | R29: =M29*(1+Assumptions!G19) -> 13528.186 | S29: =N29*(1+Assumptions!H19) -> 14189.249 | T29: =O29*(1+Assumptions!I19) -> 14574.455 | U29: =P29*(1+Assumptions!J19) -> 14321.959 | V29: =SUM(R29:U29) -> 56613.85
A30: Selling, General & Administrative | B30: 26097 | C30: 7175 | D30: 6728 | E30: 6650 | F30: 7048 | G30: =SUM(C30:F30) -> 27601 | H30: 7492 | I30: 7477 | J30: 7346 | K30: =F30*(1+Assumptions!B20) -> 7682.32 | L30: =SUM(H30:K30) -> 29997.32 | M30: =H30*(1+Assumptions!C20) -> 8053.9 | N30: =I30*(1+Assumptions!D20) -> 8037.775 | O30: =J30*(1+Assumptions!E20) -> 7896.95 | P30: =K30*(1+Assumptions!F20) -> 8258.494 | Q30: =SUM(M30:P30) -> 32247.119 | R30: =M30*(1+Assumptions!G20) -> 8577.4035 | S30: =N30*(1+Assumptions!H20) -> 8560.2304 | T30: =O30*(1+Assumptions!I20) -> 8410.2517 | U30: =P30*(1+Assumptions!J20) -> 8795.2961 | V30: =SUM(R30:U30) -> 34343.182
A31: Total Operating Expenses | B31: =B29+B30 -> 57467 | C31: =C29+C30 -> 15443 | D31: =D29+D30 -> 15278 | E31: =E29+E30 -> 15516 | F31: =F29+F30 -> 15914 | G31: =G29+G30 -> 62151 | H31: =H29+H30 -> 18379 | I31: =I29+I30 -> 18896 | ... V31: =V29+V30 -> 90957.032
A33: Operating Income | B33: =B23-B31 -> 123216 | C33: =C23-C31 -> 42832 | D33: =D23-D31 -> 29589 | E33: =E23-E31 -> 28202 | F33: =F23-F31 -> 32427 | G33: =G23-G31 -> 133050 | H33: =H23-H31 -> 50852 | I33: =I23-I31 -> 35885 | ... V33: =V23-V31 -> 180153.75
A34: Operating Margin % | B34: =IFERROR(B33/B15,"") -> 0.31510223 | C34: =IFERROR(C33/C15,"") -> 0.34458568 | D34: =IFERROR(D33/D15,"") -> 0.31029059 | E34: =IFERROR(E33/E15,"") -> 0.29990642 | F34: =IFERROR(F33/F15,"") -> 0.31646595 | G34: =IFERROR(G33/G15,"") -> 0.319708 | H34: =IFERROR(H33/H15,"") -> 0.35373828 | I34: =IFERROR(I33/I15,"") -> 0.32275327 | ... V34: =IFERROR(V33/V15,"") -> 0.32629607
A36: Other Income/(Expense), net | B36: 269 | C36: -248 | D36: -279 | E36: -171 | F36: 377 | G36: =SUM(C36:F36) -> -321 | H36: 150 | I36: -52 | J36: 572 | K36: =Assumptions!B23 -> 200 | L36: =SUM(H36:K36) -> 870 | M36: =Assumptions!C23 -> 200 | N36: =Assumptions!D23 -> 200 | O36: =Assumptions!E23 -> 200 | P36: =Assumptions!F23 -> 200 | Q36: =SUM(M36:P36) -> 800 | R36: =Assumptions!G23 -> 225 | S36: =Assumptions!H23 -> 225 | T36: =Assumptions!I23 -> 225 | U36: =Assumptions!J23 -> 225 | V36: =SUM(R36:U36) -> 900
A37: Income Before Provision for Income Taxes | B37: =B33+B36 -> 123485 | C37: =C33+C36 -> 42584 | D37: =D33+D36 -> 29310 | E37: =E33+E36 -> 28031 | F37: =F33+F36 -> 32804 | G37: =G33+G36 -> 132729 | H37: =H33+H36 -> 51002 | I37: =I33+I36 -> 35833 | ... V37: =V33+V36 -> 181053.75
A38: Provision for Income Taxes | B38: 29749 | C38: 6254 | D38: 4530 | E38: 4597 | F38: 5338 | G38: =SUM(C38:F38) -> 20719 | H38: 8905 | I38: 6255 | J38: 6478 | K38: =K37*Assumptions!B24 -> 6080.638 | L38: =SUM(H38:K38) -> 27718.638 | M38: =M37*Assumptions!C24 -> 9015.5627 | N38: =N37*Assumptions!D24 -> 6663.6043 | O38: =O37*Assumptions!E24 -> 6479.3024 | P38: =P37*Assumptions!F24 -> 6813.1806 | Q38: =SUM(M38:P38) -> 28971.65 | R38: =R37*Assumptions!G24 -> 9813.697 | S38: =S37*Assumptions!H24 -> 7302.1325 | T38: =T37*Assumptions!I24 -> 7101.127 | U38: =U37*Assumptions!J24 -> 7467.4489 | V38: =SUM(R38:U38) -> 31684.405
A39: Effective Tax Rate % | B39: =IFERROR(B38/B37,"") -> 0.24091185 | C39: =IFERROR(C38/C37,"") -> 0.14686267 | D39: =IFERROR(D38/D37,"") -> 0.15455476 | E39: =IFERROR(E38/E37,"") -> 0.163997 | F39: =IFERROR(F38/F37,"") -> 0.16272406 | G39: =IFERROR(G38/G37,"") -> 0.15610002 | H39: =IFERROR(H38/H37,"") -> 0.174601 | I39: =IFERROR(I38/I37,"") -> 0.17455976 | ... V39: =IFERROR(V38/V37,"") -> 0.175
A40: Net Income | B40: =B37-B38 -> 93736 | C40: =C37-C38 -> 36330 | D40: =D37-D38 -> 24780 | E40: =E37-E38 -> 23434 | F40: =F37-F38 -> 27466 | G40: =G37-G38 -> 112010 | H40: =H37-H38 -> 42097 | I40: =I37-I38 -> 29578 | ... V40: =V37-V38 -> 149369.34
A41: Net Margin % | B41: =IFERROR(B40/B15,"") -> 0.23971256 | C41: =IFERROR(C40/C15,"") -> 0.29227675 | D41: =IFERROR(D40/D15,"") -> 0.25986011 | E41: =IFERROR(E40/E15,"") -> 0.24920243 | F41: =IFERROR(F40/F15,"") -> 0.26804989 | G41: =IFERROR(G40/G15,"") -> 0.26915064 | H41: =IFERROR(H40/H15,"") -> 0.29283647 | I41: =IFERROR(I40/I15,"") -> 0.26602749 | ... V41: =IFERROR(V40/V15,"") -> 0.27053908
A43: Per-Share Data
A44: Diluted Weighted-Average Shares (000s) | B44: 15408095 | C44: 15150865 | D44: 15056133 | E44: 14948179 | F44: 14863609 | G44: =AVERAGE(C44:F44) -> 15004696 | H44: 14810356 | I44: 14725873 | J44: 14714676 | K44: =J44*(1+Assumptions!B25) -> 14663175 | L44: =AVERAGE(H44:K44) -> 14728520 | M44: =K44*(1+Assumptions!C25) -> 14611854 | N44: =M44*(1+Assumptions!D25) -> 14560712 | O44: =N44*(1+Assumptions!E25) -> 14509750 | P44: =O44*(1+Assumptions!F25) -> 14458965 | Q44: =AVERAGE(M44:P44) -> 14535320 | R44: =P44*(1+Assumptions!G25) -> 14408359 | S44: =R44*(1+Assumptions!H25) -> 14357930 | T44: =S44*(1+Assumptions!I25) -> 14307677 | U44: =T44*(1+Assumptions!J25) -> 14257600 | V44: =AVERAGE(R44:U44) -> 14332892
A45: Diluted EPS | B45: =IFERROR(B40*1000/B44,"") -> 6.0835554 | C45: =IFERROR(C40*1000/C44,"") -> 2.3978829 | D45: =IFERROR(D40*1000/D44,"") -> 1.6458409 | E45: =IFERROR(E40*1000/E44,"") -> 1.5676826 | F45: =IFERROR(F40*1000/F44,"") -> 1.8478688 | G45: =IFERROR(G40*1000/G44,"") -> 7.464996 | H45: =IFERROR(H40*1000/H44,"") -> 2.842403 | I45: =IFERROR(I40*1000/I44,"") -> 2.0085736 | ... V45: =IFERROR(V40*1000/V44,"") -> 10.421438
A46: Basic Weighted-Average Shares (000s) | B46: 15343783 | C46: 15081724 | D46: 14994082 | E46: 14902886 | F46: 14815307 | G46: =AVERAGE(C46:F46) -> 14948500 | H46: 14748158 | I46: 14673278 | J46: 14656110 | K46: =K44*Assumptions!B26 -> 14604522 | L46: =AVERAGE(H46:K46) -> 14670517 | M46: =M44*Assumptions!C26 -> 14553406 | N46: =N44*Assumptions!D26 -> 14502469 | O46: =O44*Assumptions!E26 -> 14451711 | P46: =P44*Assumptions!F26 -> 14401130 | Q46: =AVERAGE(M46:P46) -> 14477179 | R46: =R44*Assumptions!G26 -> 14350726 | S46: =S44*Assumptions!H26 -> 14300498 | T46: =T44*Assumptions!I26 -> 14250446 | U46: =U44*Assumptions!J26 -> 14200570 | V46: =AVERAGE(R46:U46) -> 14275560
A47: Basic EPS | B47: =IFERROR(B40*1000/B46,"") -> 6.1090541 | C47: =IFERROR(C40*1000/C46,"") -> 2.4088758 | D47: =IFERROR(D40*1000/D46,"") -> 1.652652 | E47: =IFERROR(E40*1000/E46,"") -> 1.5724471 | F47: =IFERROR(F40*1000/F46,"") -> 1.8538934 | G47: =IFERROR(G40*1000/G46,"") -> 7.4930596 | H47: =IFERROR(H40*1000/H46,"") -> 2.8543904 | I47: =IFERROR(I40*1000/I46,"") -> 2.0157732 | ... V47: =IFERROR(V40*1000/V46,"") -> 10.463291

Sheet Notes & Sources
A1: Apple Inc. (AAPL) — Model Notes & Sources
A3: Color legend (Income Statement tab)
A4: Blue text = hardcoded actual figures sourced directly from Apple's SEC filings (10-K/10-Q) and quarterly press-release financial statements.
A5: Black text = formula calculated from other cells on the same sheet (e.g. subtotals, margins, EPS).
A6: Green text = formula that pulls a growth rate, margin, or ratio assumption from the Assumptions tab (forecast periods only).
A8: Historical data sources
A9: FY2024 (annual) and FY2025 Q1-Q4: Apple Inc. Condensed Consolidated Statements of Operations, quarterly press releases (apple.com/newsroom) and Form 10-K (fiscal year ended September 27, 2025), filed with the SEC.
A10: FY2026 Q1 (qtr ended Dec 27, 2025), Q2 (qtr ended Mar 28, 2026), Q3 (qtr ended Jun 27, 2026): Apple Inc. Condensed Consolidated Statements of Operations, quarterly press releases and Forms 10-Q filed with the SEC.
A11: All historical figures reconcile exactly to Apple's reported quarterly and annual totals (net sales, cost of sales, operating expenses, tax provision, net income).
A13: Forecast basis (Q4 FY2026E onward)
A14: Q4 FY2026E: informed by Apple management's guidance given on the July 30, 2026 Q3 FY2026 earnings call — total revenue growth of 9-11% YoY, gross margin of 47-48% (including ~1 pt of tariff-refund benefit), and iPhone revenue growth in the mid-teens YoY, tempered by cited FX headwinds (~2.5 pts) and increasing supply constraints.
A15: FY2027E-FY2028E: iPhone growth normalizes from the elevated iPhone 17 upgrade cycle towards high-single-digit then mid-single-digit growth; Services continues durable low-double-digit growth; Mac/iPad/Wearables grow at low-single-digit rates consistent with mature-category trends; Products gross margin assumed to expand modestly via mix shift (excluding one-time tariff-refund effects).
... A23: Annual (FY) diluted/basic share counts are approximated as the simple average of the four quarterly weighted-average share counts, which may differ slightly from Apple's own full-year weighted-average share count disclosure.
