Workbook

Sheet Cover
B2: Apple Inc. (AAPL) — Income Statement Forecast
B3: Fiscal Years 2026–2028, Quarterly Detail
B5: Prepared: August 16, 2026
B7: Fiscal calendar
B8: Apple's fiscal year ends the last Saturday of September. FY2026 = Oct 2025–Sep 2026, FY2027 = Oct 2026–Sep 2027, FY2028 = Oct 2027–Sep 2028. Quarters are ~13 weeks each.
B10: Actuals basis
B11: FY2024, FY2025, and FY2026 Q1–Q3 are actual reported results, sourced directly from Apple's SEC Form 8-K Exhibit 99.1 press releases and Form 10-K/10-Q filings (condensed consolidated statements of operations). Figures are in millions of USD except per-share amounts and percentages.
B13: Forecast basis
B14: FY2026 Q4 through FY2028 Q4 (9 quarters) are forecast using explicit driver assumptions on the Assumptions tab: Products/Services revenue growth (YoY), Products/Services gross margin, R&D and SG&A as % of revenue, effective tax rate, and annual diluted share count reduction from buybacks.
B16: FY2026 Q4 guidance
B17: Apple's CFO guided (July 30, 2026 earnings call) to September-quarter total revenue growth of 9%–11% YoY and gross margin of 47%–48% (including ~1pt tariff-refund benefit, offset by FX and component-cost headwinds). The FY2026 Q4 assumptions below are calibrated to this guidance.
B19: FY2027–FY2028 trajectory
... B31: Black text = live formula

Sheet Assumptions
A1: AAPL Forecast Assumptions — FY2026 Q4 through FY2028 Q4
A3: Fiscal Quarter | B3: Products Net Sales Growth (YoY) | C3: Services Net Sales Growth (YoY) | D3: Products Gross Margin % | E3: Services Gross Margin % | F3: R&D (% of Net Sales) | G3: SG&A (% of Net Sales) | H3: Other Income/(Exp) (% of Net Sales) | I3: Effective Tax Rate | J3: Diluted Share Count Reduction (YoY, buybacks)
A4: FY2026 Q4 | B4: 0.09 | C4: 0.13 | D4: 0.358 | E4: 0.765 | F4: 0.089 | G4: 0.066 | H4: 0.001 | I4: 0.18 | J4: 0.02
A5: FY2027 Q1 | B5: 0.08 | C5: 0.13 | D5: 0.365 | E5: 0.765 | F5: 0.077 | G5: 0.052 | H5: 0.001 | I5: 0.18 | J5: 0.02
A6: FY2027 Q2 | B6: 0.08 | C6: 0.13 | D6: 0.37 | E6: 0.767 | F6: 0.103 | G6: 0.066 | H6: 0.001 | I6: 0.18 | J6: 0.02
A7: FY2027 Q3 | B7: 0.08 | C7: 0.13 | D7: 0.375 | E7: 0.768 | F7: 0.107 | G7: 0.066 | H7: 0.001 | I7: 0.18 | J7: 0.02
A8: FY2027 Q4 | B8: 0.08 | C8: 0.13 | D8: 0.38 | E8: 0.77 | F8: 0.089 | G8: 0.066 | H8: 0.001 | I8: 0.18 | J8: 0.02
A9: FY2028 Q1 | B9: 0.06 | C9: 0.12 | D9: 0.385 | E9: 0.77 | F9: 0.077 | G9: 0.052 | H9: 0.001 | I9: 0.18 | J9: 0.02
A10: FY2028 Q2 | B10: 0.06 | C10: 0.12 | D10: 0.39 | E10: 0.772 | F10: 0.103 | G10: 0.066 | H10: 0.001 | I10: 0.18 | J10: 0.02
A11: FY2028 Q3 | B11: 0.06 | C11: 0.12 | D11: 0.395 | E11: 0.773 | F11: 0.107 | G11: 0.066 | H11: 0.001 | I11: 0.18 | J11: 0.02
A12: FY2028 Q4 | B12: 0.06 | C12: 0.12 | D12: 0.4 | E12: 0.775 | F12: 0.089 | G12: 0.066 | H12: 0.001 | I12: 0.18 | J12: 0.02
A15: Notes:
A16: • FY2026 Q4 growth/margin assumptions are calibrated to Apple's official guidance from the July 30, 2026 Q3 FY2026 earnings call: total revenue +9%–11% YoY, gross margin 47%–48% (incl. ~1pt tariff-refund benefit).
A17: • Products revenue growth decelerates from FY2026's iPhone 17 / Apple Intelligence upgrade-cycle pace (+16-18% YoY in Q1-Q3 FY2026) toward high-single-digit growth as compares normalize through FY2027-FY2028.
A18: • Services revenue growth assumed to continue its steady low-teens YoY pace, consistent with FY2025-FY2026 actuals (App Store, advertising, AppleCare, subscriptions).
A19: • Products gross margin assumed to trough with FY2026 Q4 guidance (component/memory cost inflation, FX headwind), then recover gradually through FY2027-FY2028 as costs normalize and mix improves.
A20: • Effective tax rate held at 18.0%, in line with the FY2026 run-rate of 17.5-17.9% (up from FY2025's 15.6%, reflecting global minimum tax / Pillar Two phase-in).
A21: • Diluted share count assumed to shrink 2.0% YoY per quarter from continued buybacks, in line with the recent 1.6-2.7% annual pace observed FY2024-FY2026.
A22: • R&D and SG&A % of revenue assumptions hold each fiscal quarter at its trailing same-quarter-type actual ratio (Q1 revenue-heavy quarters dilute opex ratios; Q2/Q3 run higher R&D intensity), consistent with FY2024-FY2026 seasonal patterns.

Sheet Quarterly Model
A1: Apple Inc. — Quarterly Income Statement: Actuals (FY2024–FY2026 Q3) & Forecast (FY2026 Q4–FY2028)
B5: FY2024 (Actual) | G5: FY2025 (Actual) | L5: FY2026 (Actual Q1-Q3 / Forecast Q4) | Q5: FY2027 (Forecast) | V5: FY2028 (Forecast)
B6: Q1 | C6: Q2 | D6: Q3 | E6: Q4 | F6: FY Total | G6: Q1 | H6: Q2 | I6: Q3 | J6: Q4 | K6: FY Total | L6: Q1 | M6: Q2 | N6: Q3 | O6: Q4 | P6: FY Total | Q6: Q1 | R6: Q2 | S6: Q3 | T6: Q4 | U6: FY Total | V6: Q1 | W6: Q2 | X6: Q3 | Y6: Q4 | Z6: FY Total
B7: Dec-23 | C7: Mar-24 | D7: Jun-24 | E7: Sep-24 | G7: Dec-24 | H7: Mar-25 | I7: Jun-25 | J7: Sep-25 | L7: Dec-25 | M7: Mar-26 | N7: Jun-26 | O7: Sep-26 (E) | Q7: Dec-26 (E) | R7: Mar-27 (E) | S7: Jun-27 (E) | T7: Sep-27 (E) | V7: Dec-27 (E) | W7: Mar-28 (E) | X7: Jun-28 (E) | Y7: Sep-28 (E)
A9: Net Sales — Products | B9: 96458 | C9: 66886 | D9: 61564 | E9: 69958 | F9: =B9+C9+D9+E9 -> 294866 | G9: 97960 | H9: 68714 | I9: 66613 | J9: 73716 | K9: =G9+H9+I9+J9 -> 307003 | L9: 113743 | M9: 80208 | N9: 78678 | O9: =J9*(1+Assumptions!B4) -> 80350.44 | P9: =L9+M9+N9+O9 -> 352979.44 | Q9: =L9*(1+Assumptions!B5) -> 122842.44 | R9: =M9*(1+Assumptions!B6) -> 86624.64 | S9: =N9*(1+Assumptions!B7) -> 84972.24 | T9: =O9*(1+Assumptions!B8) -> 86778.475 | U9: =Q9+R9+S9+T9 -> 381217.8 | V9: =Q9*(1+Assumptions!B9) -> 130212.99 | W9: =R9*(1+Assumptions!B10) -> 91822.118 | X9: =S9*(1+Assumptions!B11) -> 90070.574 | Y9: =T9*(1+Assumptions!B12) -> 91985.184 | Z9: =V9+W9+X9+Y9 -> 404090.86
A10: Net Sales — Services | B10: 23117 | C10: 23867 | D10: 24213 | E10: 24972 | F10: =B10+C10+D10+E10 -> 96169 | G10: 26340 | H10: 26645 | I10: 27423 | J10: 28750 | K10: =G10+H10+I10+J10 -> 109158 | L10: 30013 | M10: 30976 | N10: 30739 | O10: =J10*(1+Assumptions!C4) -> 32487.5 | P10: =L10+M10+N10+O10 -> 124215.5 | Q10: =L10*(1+Assumptions!C5) -> 33914.69 | R10: =M10*(1+Assumptions!C6) -> 35002.88 | S10: =N10*(1+Assumptions!C7) -> 34735.07 | T10: =O10*(1+Assumptions!C8) -> 36710.875 | U10: =Q10+R10+S10+T10 -> 140363.52 | V10: =Q10*(1+Assumptions!C9) -> 37984.453 | W10: =R10*(1+Assumptions!C10) -> 39203.226 | X10: =S10*(1+Assumptions!C11) -> 38903.278 | Y10: =T10*(1+Assumptions!C12) -> 41116.18 | Z10: =V10+W10+X10+Y10 -> 157207.14
A11: Total Net Sales | B11: =B9+B10 -> 119575 | C11: =C9+C10 -> 90753 | D11: =D9+D10 -> 85777 | E11: =E9+E10 -> 94930 | F11: =F9+F10 -> 391035 | G11: =G9+G10 -> 124300 | H11: =H9+H10 -> 95359 | I11: =I9+I10 -> 94036 | ... Z11: =Z9+Z10 -> 561298
A12: YoY Growth % | G12: =G11/B11-1 -> 0.039514949 | H12: =H11/C11-1 -> 0.050753143 | I12: =I11/D11-1 -> 0.096284552 | J12: =J11/E11-1 -> 0.07938481 | K12: =K11/F11-1 -> 0.064255118 | L12: =L11/G11-1 -> 0.15652454 | M12: =M11/H11-1 -> 0.16595182 | N12: =N11/I11-1 -> 0.16356502 | ... Z12: =Z11/U11-1 -> 0.076146688
A14: Cost of Sales — Products | B14: 58440 | C14: 42424 | D14: 39803 | E14: 44566 | F14: =B14+C14+D14+E14 -> 185233 | G14: 59447 | H14: 44030 | I14: 43620 | J14: 47019 | K14: =G14+H14+I14+J14 -> 194116 | L14: 67478 | M14: 49179 | N14: 47153 | O14: =O9*(1-Assumptions!D4) -> 51584.982 | P14: =L14+M14+N14+O14 -> 215394.98 | Q14: =Q9*(1-Assumptions!D5) -> 78004.949 | R14: =R9*(1-Assumptions!D6) -> 54573.523 | S14: =S9*(1-Assumptions!D7) -> 53107.65 | T14: =T9*(1-Assumptions!D8) -> 53802.655 | U14: =Q14+R14+S14+T14 -> 239488.78 | V14: =V9*(1-Assumptions!D9) -> 80080.987 | W14: =W9*(1-Assumptions!D10) -> 56011.492 | X14: =X9*(1-Assumptions!D11) -> 54492.698 | Y14: =Y9*(1-Assumptions!D12) -> 55191.11 | Z14: =V14+W14+X14+Y14 -> 245776.29
A15: Cost of Sales — Services | B15: 6280 | C15: 6058 | D15: 6296 | E15: 6485 | F15: =B15+C15+D15+E15 -> 25119 | G15: 6578 | H15: 6462 | I15: 6698 | J15: 7106 | K15: =G15+H15+I15+J15 -> 26844 | L15: 7047 | M15: 7224 | N15: 7494 | O15: =O10*(1-Assumptions!E4) -> 7634.5625 | P15: =L15+M15+N15+O15 -> 29399.562 | Q15: =Q10*(1-Assumptions!E5) -> 7969.9522 | R15: =R10*(1-Assumptions!E6) -> 8155.671 | S15: =S10*(1-Assumptions!E7) -> 8058.5362 | T15: =T10*(1-Assumptions!E8) -> 8443.5012 | U15: =Q15+R15+S15+T15 -> 32627.661 | V15: =V10*(1-Assumptions!E9) -> 8736.4241 | W15: =W10*(1-Assumptions!E10) -> 8938.3354 | X15: =X10*(1-Assumptions!E11) -> 8831.0442 | Y15: =Y10*(1-Assumptions!E12) -> 9251.1405 | Z15: =V15+W15+X15+Y15 -> 35756.944
A16: Total Cost of Sales | B16: =B14+B15 -> 64720 | C16: =C14+C15 -> 48482 | D16: =D14+D15 -> 46099 | E16: =E14+E15 -> 51051 | F16: =F14+F15 -> 210352 | G16: =G14+G15 -> 66025 | H16: =H14+H15 -> 50492 | I16: =I14+I15 -> 50318 | ... Z16: =Z14+Z15 -> 281533.23
A17: Gross Margin ($) | B17: =B11-B16 -> 54855 | C17: =C11-C16 -> 42271 | D17: =D11-D16 -> 39678 | E17: =E11-E16 -> 43879 | F17: =F11-F16 -> 180683 | G17: =G11-G16 -> 58275 | H17: =H11-H16 -> 44867 | I17: =I11-I16 -> 43718 | ... Z17: =Z11-Z16 -> 279764.77
A18: Gross Margin % | B18: =B17/B11 -> 0.45874974 | C18: =C17/C11 -> 0.46578075 | D18: =D17/D11 -> 0.46257155 | E18: =E17/E11 -> 0.4622248 | F18: =F17/F11 -> 0.4620635 | G18: =G17/G11 -> 0.46882542 | H18: =H17/H11 -> 0.47050619 | I18: =I17/I11 -> 0.46490706 | ... Z18: =Z17/Z11 -> 0.49842467
A20: Research & Development | B20: 7696 | C20: 7903 | D20: 8006 | E20: 7765 | F20: =B20+C20+D20+E20 -> 31370 | G20: 8268 | H20: 8550 | I20: 8866 | J20: 8866 | K20: =G20+H20+I20+J20 -> 34550 | L20: 10887 | M20: 11419 | N20: 11729 | O20: =O11*Assumptions!F4 -> 10042.577 | P20: =L20+M20+N20+O20 -> 44077.577 | Q20: =Q11*Assumptions!F5 -> 12070.299 | R20: =R11*Assumptions!F6 -> 12527.635 | S20: =S11*Assumptions!F7 -> 12808.682 | T20: =T11*Assumptions!F8 -> 10990.552 | U20: =Q20+R20+S20+T20 -> 48397.168 | V20: =V11*Assumptions!F9 -> 12951.203 | W20: =W11*Assumptions!F10 -> 13495.61 | X20: =X11*Assumptions!F11 -> 13800.202 | Y20: =Y11*Assumptions!F12 -> 11846.021 | Z20: =V20+W20+X20+Y20 -> 52093.037
A21: Selling, General & Administrative | B21: 6786 | C21: 6468 | D21: 6320 | E21: 6523 | F21: =B21+C21+D21+E21 -> 26097 | G21: 7175 | H21: 6728 | I21: 6650 | J21: 7048 | K21: =G21+H21+I21+J21 -> 27601 | L21: 7492 | M21: 7477 | N21: 7346 | O21: =O11*Assumptions!G4 -> 7447.304 | P21: =L21+M21+N21+O21 -> 29762.304 | Q21: =Q11*Assumptions!G5 -> 8151.3708 | R21: =R11*Assumptions!G6 -> 8027.4163 | S21: =S11*Assumptions!G7 -> 7900.6825 | T21: =T11*Assumptions!G8 -> 8150.2971 | U21: =Q21+R21+S21+T21 -> 32229.767 | V21: =V11*Assumptions!G9 -> 8746.2668 | W21: =W11*Assumptions!G10 -> 8647.6727 | X21: =X11*Assumptions!G11 -> 8512.2743 | Y21: =Y11*Assumptions!G12 -> 8784.69 | Z21: =V21+W21+X21+Y21 -> 34690.904
A22: Total Operating Expenses | B22: =B20+B21 -> 14482 | C22: =C20+C21 -> 14371 | D22: =D20+D21 -> 14326 | E22: =E20+E21 -> 14288 | F22: =F20+F21 -> 57467 | G22: =G20+G21 -> 15443 | H22: =H20+H21 -> 15278 | I22: =I20+I21 -> 15516 | ... Z22: =Z20+Z21 -> 86783.941
A23: Operating Income | B23: =B17-B22 -> 40373 | C23: =C17-C22 -> 27900 | D23: =D17-D22 -> 25352 | E23: =E17-E22 -> 29591 | F23: =F17-F22 -> 123216 | G23: =G17-G22 -> 42832 | H23: =H17-H22 -> 29589 | I23: =I17-I22 -> 28202 | ... Z23: =Z17-Z22 -> 192980.83
A24: Operating Margin % | B24: =B23/B11 -> 0.33763747 | C24: =C23/C11 -> 0.30742785 | D24: =D23/D11 -> 0.29555708 | E24: =E23/E11 -> 0.31171389 | F24: =F23/F11 -> 0.31510223 | G24: =G23/G11 -> 0.34458568 | H24: =H23/H11 -> 0.31029059 | I24: =I23/I11 -> 0.29990642 | ... Z24: =Z23/Z11 -> 0.34381172
A26: Other Income/(Expense), net | B26: -50 | C26: 158 | D26: 142 | E26: 19 | F26: =B26+C26+D26+E26 -> 269 | G26: -248 | H26: -279 | I26: -171 | J26: 377 | K26: =G26+H26+I26+J26 -> -321 | L26: 150 | M26: -52 | N26: 572 | O26: =O11*Assumptions!H4 -> 112.83794 | P26: =L26+M26+N26+O26 -> 782.83794 | Q26: =Q11*Assumptions!H5 -> 156.75713 | R26: =R11*Assumptions!H6 -> 121.62752 | S26: =S11*Assumptions!H7 -> 119.70731 | T26: =T11*Assumptions!H8 -> 123.48935 | U26: =Q26+R26+S26+T26 -> 521.58131 | V26: =V11*Assumptions!H9 -> 168.19744 | W26: =W11*Assumptions!H10 -> 131.02534 | X26: =X11*Assumptions!H11 -> 128.97385 | Y26: =Y11*Assumptions!H12 -> 133.10136 | Z26: =V26+W26+X26+Y26 -> 561.298
A27: Income Before Provision for Income Taxes | B27: =B23+B26 -> 40323 | C27: =C23+C26 -> 28058 | D27: =D23+D26 -> 25494 | E27: =E23+E26 -> 29610 | F27: =F23+F26 -> 123485 | G27: =G23+G26 -> 42584 | H27: =H23+H26 -> 29310 | I27: =I23+I26 -> 28031 | ... Z27: =Z23+Z26 -> 193542.13
A28: Provision for Income Taxes | B28: 6407 | C28: 4422 | D28: 4046 | E28: 14874 | F28: =B28+C28+D28+E28 -> 29749 | G28: 6254 | H28: 4530 | I28: 4597 | J28: 5338 | K28: =G28+H28+I28+J28 -> 20719 | L28: 8905 | M28: 6255 | N28: 6478 | O28: =O27*Assumptions!I4 -> 6523.4434 | P28: =L28+M28+N28+O28 -> 28161.443 | Q28: =Q27*Assumptions!I5 -> 9129.1168 | R28: =R27*Assumptions!I6 -> 6923.6824 | S28: =S27*Assumptions!I7 -> 6831.264 | T28: =T27*Assumptions!I8 -> 7600.6502 | U28: =Q28+R28+S28+T28 -> 30484.713 | V28: =V27*Assumptions!I9 -> 10413.136 | W28: =W27*Assumptions!I10 -> 7931.3865 | X28: =X27*Assumptions!I11 -> 7823.9895 | Y28: =Y27*Assumptions!I12 -> 8669.0705 | Z28: =V28+W28+X28+Y28 -> 34837.583
A29: Effective Tax Rate % | B29: =B28/B27 -> 0.15889195 | C29: =C28/C27 -> 0.15760211 | D29: =D28/D27 -> 0.15870401 | E29: =E28/E27 -> 0.50233029 | F29: =F28/F27 -> 0.24091185 | G29: =G28/G27 -> 0.14686267 | H29: =H28/H27 -> 0.15455476 | I29: =I28/I27 -> 0.163997 | ... Z29: =Z28/Z27 -> 0.18
A30: Net Income | B30: =B27-B28 -> 33916 | C30: =C27-C28 -> 23636 | D30: =D27-D28 -> 21448 | E30: =E27-E28 -> 14736 | F30: =F27-F28 -> 93736 | G30: =G27-G28 -> 36330 | H30: =H27-H28 -> 24780 | I30: =I27-I28 -> 23434 | ... Z30: =Z27-Z28 -> 158704.54
A31: Net Margin % | B31: =B30/B11 -> 0.28363788 | C31: =C30/C11 -> 0.26044318 | D31: =D30/D11 -> 0.25004372 | E31: =E30/E11 -> 0.15523017 | F31: =F30/F11 -> 0.23971256 | G31: =G30/G11 -> 0.29227675 | H31: =H30/H11 -> 0.25986011 | I31: =I30/I11 -> 0.24920243 | ... Z31: =Z30/Z11 -> 0.28274561
A33: Diluted Weighted-Avg Shares (M) | B33: 15576.641 | C33: 15464.709 | D33: 15348.175 | E33: 15242.853 | F33: =AVERAGE(B33:E33) -> 15408.094 | G33: 15150.865 | H33: 15056.133 | I33: 14948.179 | J33: 14863.609 | K33: =AVERAGE(G33:J33) -> 15004.697 | L33: 14810.356 | M33: 14725.873 | N33: 14714.676 | O33: =J33*(1-Assumptions!J4) -> 14566.337 | P33: =AVERAGE(L33:O33) -> 14704.31 | Q33: =L33*(1-Assumptions!J5) -> 14514.149 | R33: =M33*(1-Assumptions!J6) -> 14431.356 | S33: =N33*(1-Assumptions!J7) -> 14420.382 | T33: =O33*(1-Assumptions!J8) -> 14275.01 | U33: =AVERAGE(Q33:T33) -> 14410.224 | V33: =Q33*(1-Assumptions!J9) -> 14223.866 | W33: =R33*(1-Assumptions!J10) -> 14142.728 | X33: =S33*(1-Assumptions!J11) -> 14131.975 | Y33: =T33*(1-Assumptions!J12) -> 13989.51 | Z33: =AVERAGE(V33:Y33) -> 14122.02
A34: Basic Weighted-Avg Shares (M) | B34: 15509.763 | C34: 15405.856 | D34: 15287.521 | E34: 15171.99 | F34: =AVERAGE(B34:E34) -> 15343.782 | G34: 15081.724 | H34: 14994.082 | I34: 14902.886 | J34: 14815.307 | K34: =AVERAGE(G34:J34) -> 14948.5 | L34: 14748.158 | M34: 14673.278 | N34: 14656.11 | O34: =J34*(1-Assumptions!J4) -> 14519.001 | P34: =AVERAGE(L34:O34) -> 14649.137 | Q34: =L34*(1-Assumptions!J5) -> 14453.195 | R34: =M34*(1-Assumptions!J6) -> 14379.812 | S34: =N34*(1-Assumptions!J7) -> 14362.988 | T34: =O34*(1-Assumptions!J8) -> 14228.621 | U34: =AVERAGE(Q34:T34) -> 14356.154 | V34: =Q34*(1-Assumptions!J9) -> 14164.131 | W34: =R34*(1-Assumptions!J10) -> 14092.216 | X34: =S34*(1-Assumptions!J11) -> 14075.728 | Y34: =T34*(1-Assumptions!J12) -> 13944.048 | Z34: =AVERAGE(V34:Y34) -> 14069.031
A35: Diluted EPS | B35: =B30/B33 -> 2.1773629 | C35: =C30/C33 -> 1.5283831 | D35: =D30/D33 -> 1.39743 | E35: =E30/E33 -> 0.96674815 | F35: =F30/F33 -> 6.0835556 | G35: =G30/G33 -> 2.3978829 | H35: =H30/H33 -> 1.6458409 | I35: =I30/I33 -> 1.5676826 | ... Z35: =Z30/Z33 -> 11.238091
A36: Basic EPS | B36: =B30/B34 -> 2.1867517 | C36: =C30/C34 -> 1.5342218 | D36: =D30/D34 -> 1.4029744 | E36: =E30/E34 -> 0.97126349 | F36: =F30/F34 -> 6.1090543 | G36: =G30/G34 -> 2.4088758 | H36: =H30/H34 -> 1.652652 | I36: =I30/I34 -> 1.5724471 | ... Z36: =Z30/Z34 -> 11.280418
A38: Products % of Net Sales | B38: =B9/B11 -> 0.80667364 | C38: =C9/C11 -> 0.73701145 | D38: =D9/D11 -> 0.71772153 | E38: =E9/E11 -> 0.73694301 | F38: =F9/F11 -> 0.75406549 | G38: =G9/G11 -> 0.78809332 | H38: =H9/H11 -> 0.72058222 | I38: =I9/I11 -> 0.70837764 | ... Z38: =Z9/Z11 -> 0.71992215
A39: Services % of Net Sales | B39: =B10/B11 -> 0.19332636 | C39: =C10/C11 -> 0.26298855 | D39: =D10/D11 -> 0.28227847 | E39: =E10/E11 -> 0.26305699 | F39: =F10/F11 -> 0.24593451 | G39: =G10/G11 -> 0.21190668 | H39: =H10/H11 -> 0.27941778 | I39: =I10/I11 -> 0.29162236 | ... Z39: =Z10/Z11 -> 0.28007785

Sheet Annual Summary
A1: Apple Inc. — Annual Income Statement Summary (FY2024–FY2028)
B3: FY2024 | C3: FY2025 | D3: FY2026 | E3: FY2027 | F3: FY2028
B4: Actual | C4: Actual | D4: Actual thru Q3 / Fcst Q4 | E4: Forecast | F4: Forecast
A6: Net Sales — Products | B6: ='Quarterly Model'!F9 -> 294866 | C6: ='Quarterly Model'!K9 -> 307003 | D6: ='Quarterly Model'!P9 -> 352979.44 | E6: ='Quarterly Model'!U9 -> 381217.8 | F6: ='Quarterly Model'!Z9 -> 404090.86
A7: Net Sales — Services | B7: ='Quarterly Model'!F10 -> 96169 | C7: ='Quarterly Model'!K10 -> 109158 | D7: ='Quarterly Model'!P10 -> 124215.5 | E7: ='Quarterly Model'!U10 -> 140363.52 | F7: ='Quarterly Model'!Z10 -> 157207.14
A8: Total Net Sales | B8: =B6+B7 -> 391035 | C8: =C6+C7 -> 416161 | D8: =D6+D7 -> 477194.94 | E8: =E6+E7 -> 521581.31 | F8: =F6+F7 -> 561298
A9: YoY Growth % | C9: =C8/B8-1 -> 0.064255118 | D9: =D8/C8-1 -> 0.14665944 | E9: =E8/D8-1 -> 0.093015174 | F9: =F8/E8-1 -> 0.076146688
A11: Gross Margin ($) | B11: ='Quarterly Model'!F17 -> 180683 | C11: ='Quarterly Model'!K17 -> 195201 | D11: ='Quarterly Model'!P17 -> 232400.4 | E11: ='Quarterly Model'!U17 -> 249464.87 | F11: ='Quarterly Model'!Z17 -> 279764.77
A12: Gross Margin % | B12: =B11/B8 -> 0.4620635 | C12: =C11/C8 -> 0.46905164 | D12: =D11/D8 -> 0.48701354 | E12: =E11/E8 -> 0.47828568 | F12: =F11/F8 -> 0.49842467
A14: Research & Development | B14: ='Quarterly Model'!F20 -> 31370 | C14: ='Quarterly Model'!K20 -> 34550 | D14: ='Quarterly Model'!P20 -> 44077.577 | E14: ='Quarterly Model'!U20 -> 48397.168 | F14: ='Quarterly Model'!Z20 -> 52093.037
A15: Selling, General & Administrative | B15: ='Quarterly Model'!F21 -> 26097 | C15: ='Quarterly Model'!K21 -> 27601 | D15: ='Quarterly Model'!P21 -> 29762.304 | E15: ='Quarterly Model'!U21 -> 32229.767 | F15: ='Quarterly Model'!Z21 -> 34690.904
A16: Total Operating Expenses | B16: =B14+B15 -> 57467 | C16: =C14+C15 -> 62151 | D16: =D14+D15 -> 73839.881 | E16: =E14+E15 -> 80626.935 | F16: =F14+F15 -> 86783.941
A17: Operating Income | B17: =B11-B16 -> 123216 | C17: =C11-C16 -> 133050 | D17: =D11-D16 -> 158560.51 | E17: =E11-E16 -> 168837.94 | F17: =F11-F16 -> 192980.83
A18: Operating Margin % | B18: =B17/B8 -> 0.31510223 | C18: =C17/C8 -> 0.319708 | D18: =D17/D8 -> 0.33227619 | E18: =E17/E8 -> 0.32370396 | F18: =F17/F8 -> 0.34381172
A20: Other Income/(Expense), net | B20: ='Quarterly Model'!F26 -> 269 | C20: ='Quarterly Model'!K26 -> -321 | D20: ='Quarterly Model'!P26 -> 782.83794 | E20: ='Quarterly Model'!U26 -> 521.58131 | F20: ='Quarterly Model'!Z26 -> 561.298
A21: Income Before Provision for Income Taxes | B21: =B17+B20 -> 123485 | C21: =C17+C20 -> 132729 | D21: =D17+D20 -> 159343.35 | E21: =E17+E20 -> 169359.52 | F21: =F17+F20 -> 193542.13
A22: Provision for Income Taxes | B22: ='Quarterly Model'!F28 -> 29749 | C22: ='Quarterly Model'!K28 -> 20719 | D22: ='Quarterly Model'!P28 -> 28161.443 | E22: ='Quarterly Model'!U28 -> 30484.713 | F22: ='Quarterly Model'!Z28 -> 34837.583
A23: Effective Tax Rate % | B23: =B22/B21 -> 0.24091185 | C23: =C22/C21 -> 0.15610002 | D23: =D22/D21 -> 0.17673435 | E23: =E22/E21 -> 0.18 | F23: =F22/F21 -> 0.18
A24: Net Income | B24: =B21-B22 -> 93736 | C24: =C21-C22 -> 112010 | D24: =D21-D22 -> 131181.91 | E24: =E21-E22 -> 138874.81 | F24: =F21-F22 -> 158704.54
A25: Net Margin % | B25: =B24/B8 -> 0.23971256 | C25: =C24/C8 -> 0.26915064 | D25: =D24/D8 -> 0.27490214 | E25: =E24/E8 -> 0.26625725 | F25: =F24/F8 -> 0.28274561
A27: Diluted Weighted-Avg Shares (M) | B27: ='Quarterly Model'!F33 -> 15408.094 | C27: ='Quarterly Model'!K33 -> 15004.697 | D27: ='Quarterly Model'!P33 -> 14704.31 | E27: ='Quarterly Model'!U33 -> 14410.224 | F27: ='Quarterly Model'!Z33 -> 14122.02
A28: Basic Weighted-Avg Shares (M) | B28: ='Quarterly Model'!F34 -> 15343.782 | C28: ='Quarterly Model'!K34 -> 14948.5 | D28: ='Quarterly Model'!P34 -> 14649.137 | E28: ='Quarterly Model'!U34 -> 14356.154 | F28: ='Quarterly Model'!Z34 -> 14069.031
A29: Diluted EPS | B29: =B24/B27 -> 6.0835556 | C29: =C24/C27 -> 7.464996 | D29: =D24/D27 -> 8.9213234 | E29: =E24/E27 -> 9.6372411 | F29: =F24/F27 -> 11.238091
A30: Basic EPS | B30: =B24/B28 -> 6.1090543 | C30: =C24/C28 -> 7.4930596 | D30: =D24/D28 -> 8.9549242 | E30: =E24/E28 -> 9.6735383 | F30: =F24/F28 -> 11.280418
A31: Net Income YoY Growth % | C31: =C24/B24-1 -> 0.19495178 | D31: =D24/C24-1 -> 0.17116248 | E31: =E24/D24-1 -> 0.05864297 | F31: =F24/E24-1 -> 0.14278859
A32: Diluted EPS YoY Growth % | C32: =C29/B29-1 -> 0.2270778 | D32: =D29/C29-1 -> 0.19508749 | E32: =E29/D29-1 -> 0.080247929 | F32: =F29/E29-1 -> 0.16611081
